{"Q1": "A few times a week", "Q2": "Never", "Q3": "Sometimes", "Q4": "Often", "Q5": "Sometimes", "Q6": "Often", "Q7": "Rarely", "Q8": "Often", "Q9": "Never", "Q10": "Often", "results": [{"mechanics": [{"timestep": 2, "mechanic": "OgreTreasure"}, {"timestep": 2, "mechanic": "BlobPotion"}, {"timestep": 3, "mechanic": "OgreTreasure"}, {"timestep": 3, "mechanic": "BlobPotion"}, {"timestep": 5, "mechanic": "CollectTreasure"}, {"timestep": 7, "mechanic": "CollectTreasure"}, {"timestep": 10, "mechanic": "JavelinThrow"}, {"timestep": 12, "mechanic": "MinitaurHit"}, {"timestep": 18, "mechanic": "OgreHit"}, {"timestep": 19, "mechanic": "JavelinThrow"}, {"timestep": 21, "mechanic": "JavelinThrow"}, {"timestep": 22, "mechanic": "MinitaurHit"}, {"timestep": 23, "mechanic": "JavelinThrow"}, {"timestep": 30, "mechanic": "JavelinThrow"}, {"timestep": 30, "mechanic": "BlobHit"}, {"timestep": 32, "mechanic": "MinitaurHit"}, {"timestep": 33, "mechanic": "JavelinThrow"}, {"timestep": 33, "mechanic": "BlobHit"}, {"timestep": 36, "mechanic": "JavelinThrow"}, {"timestep": 37, "mechanic": "MinitaurHit"}, {"timestep": 60, "mechanic": "JavelinThrow"}, {"timestep": 61, "mechanic": "MinitaurHit"}, {"timestep": 69, "mechanic": "CollectTreasure"}, {"timestep": 74, "mechanic": "CollectTreasure"}, {"timestep": 75, "mechanic": "CollectTreasure"}, {"timestep": 77, "mechanic": "JavelinThrow"}, {"timestep": 78, "mechanic": "MinitaurHit"}, {"timestep": 79, "mechanic": "CollectTreasure"}, {"timestep": 80, "mechanic": "CollectTreasure"}, {"timestep": 82, "mechanic": "MinitaurHit"}, {"timestep": 97, "mechanic": "ReachStairs"}], "frequencies": {"OgreTreasure": 2, "BlobPotion": 2, "CollectTreasure": 7, "JavelinThrow": 9, "MinitaurHit": 7, "OgreHit": 1, "BlobHit": 2, "ReachStairs": 1}, "levelReport": {"utilityGained": 0.0, "exitUtility": 1.0, "runnerUtility": 0.020000000000000018, "loitererUtility": 98.0, "completionistUtility": 0.6214814814814814, "monsterKillerUtility": 0.72, "treasureCollectorUtility": 0.8444444444444443, "turnsTaken": 98, "health": 3, "healthLost": 7, "alive": true, "javelinsThrown": 9, "monsterKills": 3, "minitaurKnockouts": 7, "treasuresCollected": 7, "potionsTaken": 0, "totalMonsters": 6, "totalTreasures": 9, "totalPotions": 2, "timeTaken": 0.0}, "positions": [{"X": 6, "Y": 3}, {"X": 5, "Y": 3}, {"X": 4, "Y": 3}, {"X": 3, "Y": 3}, {"X": 3, "Y": 2}, {"X": 3, "Y": 1}, {"X": 2, "Y": 1}, {"X": 1, "Y": 1}, {"X": 2, "Y": 1}, {"X": 1, "Y": 1}, {"X": 1, "Y": 1}, {"X": 2, "Y": 1}, {"X": 3, "Y": 1}, {"X": 3, "Y": 2}, {"X": 3, "Y": 3}, {"X": 3, "Y": 4}, {"X": 2, "Y": 4}, {"X": 2, "Y": 5}, {"X": 2, "Y": 6}, {"X": 2, "Y": 6}, {"X": 3, "Y": 6}, {"X": 3, "Y": 6}, {"X": 2, "Y": 6}, {"X": 2, "Y": 6}, {"X": 2, "Y": 7}, {"X": 2, "Y": 8}, {"X": 3, "Y": 8}, {"X": 4, "Y": 8}, {"X": 5, "Y": 8}, {"X": 6, "Y": 8}, {"X": 6, "Y": 8}, {"X": 5, "Y": 8}, {"X": 4, "Y": 8}, {"X": 4, "Y": 8}, {"X": 5, "Y": 8}, {"X": 6, "Y": 8}, {"X": 6, "Y": 8}, {"X": 5, "Y": 8}, {"X": 6, "Y": 8}, {"X": 6, "Y": 7}, {"X": 6, "Y": 6}, {"X": 7, "Y": 6}, {"X": 7, "Y": 5}, {"X": 7, "Y": 4}, {"X": 6, "Y": 4}, {"X": 6, "Y": 3}, {"X": 5, "Y": 3}, {"X": 4, "Y": 3}, {"X": 3, "Y": 3}, {"X": 2, "Y": 3}, {"X": 2, "Y": 4}, {"X": 2, "Y": 5}, {"X": 2, "Y": 6}, {"X": 2, "Y": 7}, {"X": 2, "Y": 8}, {"X": 2, "Y": 9}, {"X": 3, "Y": 9}, {"X": 3, "Y": 8}, {"X": 4, "Y": 8}, {"X": 5, "Y": 8}, {"X": 5, "Y": 8}, {"X": 4, "Y": 8}, {"X": 5, "Y": 8}, {"X": 6, "Y": 8}, {"X": 7, "Y": 8}, {"X": 7, "Y": 9}, {"X": 7, "Y": 10}, {"X": 7, "Y": 11}, {"X": 7, "Y": 12}, {"X": 7, "Y": 13}, {"X": 7, "Y": 14}, {"X": 7, "Y": 15}, {"X": 7, "Y": 16}, {"X": 7, "Y": 17}, {"X": 8, "Y": 17}, {"X": 8, "Y": 18}, {"X": 7, "Y": 18}, {"X": 7, "Y": 18}, {"X": 7, "Y": 17}, {"X": 6, "Y": 17}, {"X": 6, "Y": 18}, {"X": 7, "Y": 18}, {"X": 7, "Y": 17}, {"X": 7, "Y": 16}, {"X": 7, "Y": 15}, {"X": 7, "Y": 14}, {"X": 7, "Y": 13}, {"X": 7, "Y": 12}, {"X": 7, "Y": 11}, {"X": 7, "Y": 10}, {"X": 7, "Y": 9}, {"X": 7, "Y": 8}, {"X": 6, "Y": 8}, {"X": 5, "Y": 8}, {"X": 4, "Y": 8}, {"X": 3, "Y": 8}, {"X": 2, "Y": 8}, {"X": 1, "Y": 8}], "levelStates": ["Health: 10 X: 6 Y: 3\nXXXXXXXXXX\nXT TX m  X\nX   XXX  X\nX     H  X\nX   XX   X\nXX XXXX XX\nX TTXXPP X\nX   XX   X\nXeo    b X\nX   XX   X\nXX XXXX XX\nX   XX   X\nX   XX   X\nX      T X\nX   XX   X\nXX XXXX XX\nX   XX   X\nXb bXXT TX\nX M XXT TX\nXXXXXXXXXX\n", "Health: 10 X: 5 Y: 3\nXXXXXXXXXX\nXT TX  m X\nX   XXX  X\nX    H   X\nX   XX   X\nXX XXXX XX\nX TTXXPP X\nX o XX b X\nXe       X\nX   XX   X\nXX XXXX XX\nX   XX   X\nX   XX   X\nX      T X\nX   XX   X\nXX XXXX XX\nX   XX   X\nXb bXXT TX\nX M XXT TX\nXXXXXXXXXX\n", "Health: 10 X: 4 Y: 3\nXXXXXXXXXX\nXT TX    X\nX   XXXm X\nX   H    X\nX   XX   X\nXX XXXX XX\nX oTXXPb X\nX   XX   X\nXe       X\nX   XX   X\nXX XXXX XX\nX   XX   X\nX   XX   X\nX      T X\nX   XX   X\nXX XXXX XX\nX   XX   X\nXb bXXT TX\nX M XXT TX\nXXXXXXXXXX\n", "Health: 10 X: 3 Y: 3\nXXXXXXXXXX\nXT TX    X\nX   XXX  X\nX  H   m X\nX   XX   X\nXX XXXX XX\nX  oXXb  X\nX   XX   X\nXe       X\nX   XX   X\nXX XXXX XX\nX   XX   X\nX   XX   X\nX      T X\nX   XX   X\nXX XXXX XX\nX   XX   X\nXb bXXT TX\nX M XXT TX\nXXXXXXXXXX\n", "Health: 10 X: 3 Y: 2\nXXXXXXXXXX\nXT TX    X\nX  HXXX  X\nX     m  X\nX   XX   X\nXX XXXX XX\nX  oXXb  X\nX   XX   X\nXe       X\nX   XX   X\nXX XXXX XX\nX   XX   X\nX   XX   X\nX      T X\nX   XX   X\nXX XXXX XX\nX   XX   X\nXb bXXT TX\nX M XXT TX\nXXXXXXXXXX\n", "Health: 10 X: 3 Y: 1\nXXXXXXXXXX\nXT  X    X\nX   XXX  X\nX    m   X\nX   XX   X\nXX XXXX XX\nX  oXXb  X\nX   XX   X\nXe       X\nX   XX   X\nXX XXXX XX\nX   XX   X\nX   XX   X\nX      T X\nX   XX   X\nXX XXXX XX\nX   XX   X\nXb bXXT TX\nX M XXT TX\nXXXXXXXXXX\n", "Health: 10 X: 2 Y: 1\nXXXXXXXXXX\nXTH X    X\nX   XXX  X\nX   m    X\nX   XX   X\nXX XXXX XX\nX  oXXb  X\nX   XX   X\nXe       X\nX   XX   X\nXX XXXX XX\nX   XX   X\nX   XX   X\nX      T X\nX   XX   X\nXX XXXX XX\nX   XX   X\nXbMbXXT TX\nX   XXT TX\nXXXXXXXXXX\n", "Health: 10 X: 1 Y: 1\nXXXXXXXXXX\nX   X    X\nX   XXX  X\nX  m     X\nX   XX   X\nXX XXXX XX\nX  oXXb  X\nX   XX   X\nXe       X\nX   XX   X\nXX XXXX XX\nX   XX   X\nX   XX   X\nX      T X\nX   XX   X\nXX XXXX XX\nX   XX   X\nXbMbXXT TX\nX   XXT TX\nXXXXXXXXXX\n", "Health: 10 X: 2 Y: 1\nXXXXXXXXXX\nX H X    X\nX  mXXX  X\nX        X\nX   XX   X\nXX XXXX XX\nX  oXXb  X\nX   XX   X\nXe       X\nX   XX   X\nXX XXXX XX\nX   XX   X\nX   XX   X\nX      T X\nX   XX   X\nXX XXXX XX\nX M XX   X\nXb bXXT TX\nX   XXT TX\nXXXXXXXXXX\n", "Health: 10 X: 1 Y: 1\nXXXXXXXXXX\nX  mX    X\nX   XXX  X\nX        X\nX   XX   X\nXX XXXX XX\nX  oXXb  X\nX   XX   X\nXe       X\nX   XX   X\nXX XXXX XX\nX   XX   X\nX   XX   X\nX      T X\nX   XX   X\nXX XXXX XX\nX M XX   X\nXb bXXT TX\nX   XXT TX\nXXXXXXXXXX\n", "Health: 10 X: 1 Y: 1\nXXXXXXXXXX\nX  mX    X\nX   XXX  X\nX        X\nX   XX   X\nXX XXXX XX\nX  oXXb  X\nX   XX   X\nXe       X\nX   XX   X\nXX XXXX XX\nX   XX   X\nX   XX   X\nX      T X\nX   XX   X\nXX XXXX XX\nX M XX   X\nXb bXXT TX\nX   XXT TX\nXXXXXXXXXX\n", "Health: 10 X: 2 Y: 1\nXXXXXXXXXX\nX HmX    X\nX   XXX  X\nX        X\nX   XX   X\nXX XXXX XX\nX  oXXb  X\nX   XX   X\nXe       X\nX   XX   X\nXX XXXX XX\nX   XX   X\nX   XX   X\nX      T X\nX   XX   X\nXXMXXXX XX\nX   XX   X\nXb bXXT TX\nX   XXT TX\nXXXXXXXXXX\n", "Health: 10 X: 3 Y: 1\nXXXXXXXXXX\nX  mX    X\nX   XXX  X\nX        X\nX   XX   X\nXX XXXX XX\nX  oXXb  X\nX   XX   X\nXe       X\nX   XX   X\nXX XXXX XX\nX   XX   X\nX   XX   X\nX      T X\nX   XX   X\nXXMXXXX XX\nX   XX   X\nXb bXXT TX\nX   XXT TX\nXXXXXXXXXX\n", "Health: 10 X: 3 Y: 2\nXXXXXXXXXX\nX  mX    X\nX  HXXX  X\nX        X\nX   XX   X\nXX XXXX XX\nX  oXXb  X\nX   XX   X\nXe       X\nX   XX   X\nXX XXXX XX\nX   XX   X\nX   XX   X\nX      T X\nX   XX   X\nXXMXXXX XX\nX   XX   X\nXb bXXT TX\nX   XXT TX\nXXXXXXXXXX\n", "Health: 10 X: 3 Y: 3\nXXXXXXXXXX\nX  mX    X\nX   XXX  X\nX  H     X\nX   XX   X\nXX XXXX XX\nX  oXXb  X\nX   XX   X\nXe       X\nX   XX   X\nXX XXXX XX\nX   XX   X\nX   XX   X\nX      T X\nX   XX   X\nXXMXXXX XX\nX   XX   X\nXb bXXT TX\nX   XXT TX\nXXXXXXXXXX\n", "Health: 10 X: 3 Y: 4\nXXXXXXXXXX\nX   X    X\nX  mXXX  X\nX        X\nX  HXX   X\nXX XXXX XX\nX  oXXb  X\nX   XX   X\nXe       X\nX   XX   X\nXX XXXX XX\nX   XX   X\nX   XX   X\nX      T X\nX   XX   X\nXXMXXXX XX\nX   XX   X\nXb bXXT TX\nX   XXT TX\nXXXXXXXXXX\n", "Health: 10 X: 2 Y: 4\nXXXXXXXXXX\nX   X    X\nX m XXX  X\nX        X\nX H XX   X\nXX XXXX XX\nX  oXXb  X\nX   XX   X\nXe       X\nX   XX   X\nXX XXXX XX\nX   XX   X\nX   XX   X\nX      T X\nX M XX   X\nXX XXXX XX\nX   XX   X\nXb bXXT TX\nX   XXT TX\nXXXXXXXXXX\n", "Health: 10 X: 2 Y: 5\nXXXXXXXXXX\nX   X    X\nX   XXX  X\nX m      X\nX   XX   X\nXXHXXXX XX\nX  oXXb  X\nX   XX   X\nXe       X\nX   XX   X\nXX XXXX XX\nX   XX   X\nX   XX   X\nX M    T X\nX   XX   X\nXX XXXX XX\nX   XX   X\nXb bXXT TX\nX   XXT TX\nXXXXXXXXXX\n", "Health: 8 X: 2 Y: 6\nXXXXXXXXXX\nX   X    X\nX   XXX  X\nX        X\nX m XX   X\nXX XXXX XX\nX  oXXb  X\nX   XX   X\nXe       X\nX   XX   X\nXX XXXX XX\nX   XX   X\nX M XX   X\nX      T X\nX   XX   X\nXX XXXX XX\nX   XX   X\nXb bXXT TX\nX   XXT TX\nXXXXXXXXXX\n", "Health: 8 X: 2 Y: 6\nXXXXXXXXXX\nX   X    X\nX   XXX  X\nX        X\nX   XX   X\nXXmXXXX XX\nX  \u221eXXb  X\nX   XX   X\nXe       X\nX   XX   X\nXX XXXX XX\nX M XX   X\nX   XX   X\nX      T X\nX   XX   X\nXX XXXX XX\nX   XX   X\nXb bXXT TX\nX   XXT TX\nXXXXXXXXXX\n", "Health: 8 X: 3 Y: 6\nXXXXXXXXXX\nX   X    X\nX   XXX  X\nX        X\nX   XX   X\nXX XXXX XX\nX  \u221eXXb  X\nX   XX   X\nXe       X\nX   XX   X\nXXMXXXX XX\nX   XX   X\nX   XX   X\nX      T X\nX   XX   X\nXX XXXX XX\nX   XX   X\nXb bXXT TX\nX   XXT TX\nXXXXXXXXXX\n", "Health: 8 X: 3 Y: 6\nXXXXXXXXXX\nX   X    X\nX   XXX  X\nX        X\nX   XX   X\nXX XXXX XX\nX  \u221eXXb  X\nX   XX   X\nXe       X\nX M XX   X\nXX XXXX XX\nX   XX   X\nX   XX   X\nX      T X\nX   XX   X\nXX XXXX XX\nX   XX   X\nXb bXXT TX\nX   XXT TX\nXXXXXXXXXX\n", "Health: 8 X: 2 Y: 6\nXXXXXXXXXX\nX   X    X\nX   XXX  X\nX        X\nX   XX   X\nXX XXXX XX\nX  \u221eXXb  X\nX   XX   X\nXeM      X\nX   XX   X\nXX XXXX XX\nX   XX   X\nX   XX   X\nX      T X\nX   XX   X\nXX XXXX XX\nX   XX   X\nXb bXXT TX\nX   XXT TX\nXXXXXXXXXX\n", "Health: 8 X: 2 Y: 6\nXXXXXXXXXX\nX   X    X\nX   XXX  X\nX        X\nX   XX   X\nXX XXXX XX\nX  \u221eXXb  X\nX   XX   X\nXe\u221e      X\nX   XX   X\nXX XXXX XX\nX   XX   X\nX   XX   X\nX      T X\nX   XX   X\nXX XXXX XX\nX   XX   X\nXb bXXT TX\nX   XXT TX\nXXXXXXXXXX\n", "Health: 8 X: 2 Y: 7\nXXXXXXXXXX\nX   X    X\nX   XXX  X\nX        X\nX   XX   X\nXX XXXX XX\nX  \u221eXXb  X\nX H XX   X\nXe\u221e      X\nX   XX   X\nXX XXXX XX\nX   XX   X\nX   XX   X\nX      T X\nX   XX   X\nXX XXXX XX\nX   XX   X\nXb bXXT TX\nX   XXT TX\nXXXXXXXXXX\n", "Health: 8 X: 2 Y: 8\nXXXXXXXXXX\nX   X    X\nX   XXX  X\nX        X\nX   XX   X\nXX XXXX XX\nX  \u221eXXb  X\nX   XX   X\nXe\u221e      X\nX   XX   X\nXX XXXX XX\nX   XX   X\nX   XX   X\nX      T X\nX   XX   X\nXX XXXX XX\nX   XX   X\nXb bXXT TX\nX   XXT TX\nXXXXXXXXXX\n", "Health: 8 X: 3 Y: 8\nXXXXXXXXXX\nX   X    X\nX   XXX  X\nX        X\nX   XX   X\nXX XXXX XX\nX  \u221eXXb  X\nX   XX   X\nXe\u221eH     X\nX   XX   X\nXX XXXX XX\nX   XX   X\nX   XX   X\nX      T X\nX   XX   X\nXX XXXX XX\nX   XX   X\nXb bXXT TX\nX   XXT TX\nXXXXXXXXXX\n", "Health: 8 X: 4 Y: 8\nXXXXXXXXXX\nX   X    X\nX   XXX  X\nX        X\nX   XX   X\nXX XXXX XX\nX  \u221eXXb  X\nX  mXX   X\nXe\u221e H    X\nX   XX   X\nXX XXXX XX\nX   XX   X\nX   XX   X\nX      T X\nX   XX   X\nXX XXXX XX\nX   XX   X\nXb bXXT TX\nX   XXT TX\nXXXXXXXXXX\n", "Health: 8 X: 5 Y: 8\nXXXXXXXXXX\nX   X    X\nX   XXX  X\nX        X\nX   XX   X\nXX XXXX XX\nX  \u221eXXb  X\nX   XX   X\nXe\u221em H   X\nX   XX   X\nXX XXXX XX\nX   XX   X\nX   XX   X\nX      T X\nX   XX   X\nXX XXXX XX\nX   XX   X\nXb bXXT TX\nX   XXT TX\nXXXXXXXXXX\n", "Health: 8 X: 6 Y: 8\nXXXXXXXXXX\nX   X    X\nX   XXX  X\nX        X\nX   XX   X\nXX XXXX XX\nX  \u221eXX   X\nX   XXb  X\nXe\u221e m H  X\nX   XX   X\nXX XXXX XX\nX   XX   X\nX   XX   X\nX      T X\nX   XX   X\nXX XXXX XX\nX   XX   X\nXb bXXT TX\nX   XXT TX\nXXXXXXXXXX\n", "Health: 5 X: 6 Y: 8\nXXXXXXXXXX\nX   X    X\nX   XXX  X\nX        X\nX   XX   X\nXX XXXX XX\nX  \u221eXX   X\nX   XXb  X\nXe\u221e m H  X\nX   XX   X\nXX XXXX XX\nX   XX   X\nX   XX   X\nX      T X\nX   XX   X\nXX XXXX XX\nX   XX   X\nXb bXXT TX\nX   XXT TX\nXXXXXXXXXX\n", "Health: 5 X: 5 Y: 8\nXXXXXXXXXX\nX   X    X\nX   XXX  X\nX        X\nX   XX   X\nXX XXXX XX\nX  \u221eXX   X\nX   XX   X\nXe\u221e mHb  X\nX   XX   X\nXX XXXX XX\nX   XX   X\nX   XX   X\nX      T X\nX   XX   X\nXX XXXX XX\nX   XX   X\nXb bXXT TX\nX   XXT TX\nXXXXXXXXXX\n", "Health: 5 X: 4 Y: 8\nXXXXXXXXXX\nX   X    X\nX   XXX  X\nX        X\nX   XX   X\nXX XXXX XX\nX  \u221eXX   X\nX   XX   X\nXe\u221e mb   X\nX   XX   X\nXX XXXX XX\nX   XX   X\nX   XX   X\nX      T X\nX   XX   X\nXX XXXX XX\nX   XX   X\nXb bXXT TX\nX   XXT TX\nXXXXXXXXXX\n", "Health: 4 X: 4 Y: 8\nXXXXXXXXXX\nX   X    X\nX   XXX  X\nX        X\nX   XX   X\nXX XXXX XX\nX  \u221eXX   X\nX   XX   X\nXe\u221e m\u221e   X\nX   XX   X\nXX XXXX XX\nX   XX   X\nX   XX   X\nX      T X\nX   XX   X\nXX XXXX XX\nX   XX   X\nXb bXXT TX\nX   XXT TX\nXXXXXXXXXX\n", "Health: 4 X: 5 Y: 8\nXXXXXXXXXX\nX   X    X\nX   XXX  X\nX        X\nX   XX   X\nXX XXXX XX\nX  \u221eXX   X\nX   XX   X\nXe\u221e m\u221e   X\nX   XX   X\nXX XXXX XX\nX   XX   X\nX   XX   X\nX      T X\nX   XX   X\nXX XXXX XX\nX   XX   X\nXb bXXT TX\nX   XXT TX\nXXXXXXXXXX\n", "Health: 4 X: 6 Y: 8\nXXXXXXXXXX\nX   X    X\nX   XXX  X\nX        X\nX   XX   X\nXX XXXX XX\nX  \u221eXX   X\nX   XX   X\nXe\u221e  \u221eH  X\nX   XX   X\nXX XXXX XX\nX   XX   X\nX   XX   X\nX      T X\nX   XX   X\nXX XXXX XX\nX   XX   X\nXb bXXT TX\nX   XXT TX\nXXXXXXXXXX\n", "Health: 4 X: 6 Y: 8\nXXXXXXXXXX\nX   X    X\nX   XXX  X\nX        X\nX   XX   X\nXX XXXX XX\nX  \u221eXX   X\nX   XX   X\nXe\u221e  \u221eH  X\nX   XX   X\nXX XXXX XX\nX   XX   X\nX   XX   X\nX      T X\nX   XX   X\nXX XXXX XX\nX   XX   X\nXb bXXT TX\nX   XXT TX\nXXXXXXXXXX\n", "Health: 4 X: 5 Y: 8\nXXXXXXXXXX\nX   X    X\nX   XXX  X\nX        X\nX   XX   X\nXX XXXX XX\nX  \u221eXX   X\nX   XX   X\nXe\u221e  \u221e   X\nX   XX   X\nXX XXXX XX\nX   XX   X\nX   XX   X\nX      T X\nX   XX   X\nXX XXXX XX\nX   XX   X\nXb bXXT TX\nX   XXT TX\nXXXXXXXXXX\n", "Health: 4 X: 6 Y: 8\nXXXXXXXXXX\nX   X    X\nX   XXX  X\nX        X\nX   XX   X\nXX XXXX XX\nX  \u221eXX   X\nX   XX   X\nXe\u221e  \u221eH  X\nX   XX   X\nXX XXXX XX\nX   XX   X\nX   XX   X\nX      T X\nX   XX   X\nXX XXXX XX\nX   XX   X\nXb bXXT TX\nX   XXT TX\nXXXXXXXXXX\n", "Health: 4 X: 6 Y: 7\nXXXXXXXXXX\nX   X    X\nX   XXX  X\nX        X\nX   XX   X\nXX XXXX XX\nX  \u221eXX   X\nX   XXH  X\nXe\u221e  \u221e   X\nX   XX   X\nXX XXXX XX\nX   XX   X\nX   XX   X\nX      T X\nX   XX   X\nXX XXXX XX\nX   XX   X\nXb bXXT TX\nX   XXT TX\nXXXXXXXXXX\n", "Health: 4 X: 6 Y: 6\nXXXXXXXXXX\nX   X    X\nX   XXX  X\nX        X\nX   XX   X\nXX XXXX XX\nX  \u221eXX   X\nX   XX   X\nXe\u221e  \u221e   X\nX   XX   X\nXX XXXX XX\nX   XX   X\nX   XX   X\nX      T X\nX   XX   X\nXX XXXX XX\nX   XX   X\nXb bXXT TX\nX   XXT TX\nXXXXXXXXXX\n", "Health: 4 X: 7 Y: 6\nXXXXXXXXXX\nX   X    X\nX   XXX  X\nX        X\nX   XX   X\nXX XXXX XX\nX  \u221eXX   X\nX   XX   X\nXe\u221e  \u221em  X\nX   XX   X\nXX XXXX XX\nX   XX   X\nX   XX   X\nX      T X\nX   XX   X\nXX XXXX XX\nX   XX   X\nXb bXXT TX\nX   XXT TX\nXXXXXXXXXX\n", "Health: 4 X: 7 Y: 5\nXXXXXXXXXX\nX   X    X\nX   XXX  X\nX        X\nX   XX   X\nXX XXXXHXX\nX  \u221eXX   X\nX   XXm  X\nXe\u221e  \u221e   X\nX   XX   X\nXX XXXX XX\nX   XX   X\nX   XX   X\nX      T X\nX   XX   X\nXX XXXX XX\nX   XX   X\nXb bXXT TX\nX   XXT TX\nXXXXXXXXXX\n", "Health: 4 X: 7 Y: 4\nXXXXXXXXXX\nX   X    X\nX   XXX  X\nX        X\nX   XX H X\nXX XXXX XX\nX  \u221eXX   X\nX   XX   X\nXe\u221e  \u221e   X\nX   XX   X\nXX XXXX XX\nX   XX   X\nX   XX   X\nX      T X\nX   XX   X\nXX XXXX XX\nX   XX   X\nXb bXXT TX\nX   XXT TX\nXXXXXXXXXX\n", "Health: 4 X: 6 Y: 4\nXXXXXXXXXX\nX   X    X\nX   XXX  X\nX        X\nX   XXH  X\nXX XXXX XX\nX  \u221eXX   X\nX   XX   X\nXe\u221e  \u221e   X\nX   XX   X\nXX XXXX XX\nX   XX   X\nX   XX   X\nX      T X\nX   XX   X\nXX XXXX XX\nX   XX   X\nXb bXXT TX\nX   XXT TX\nXXXXXXXXXX\n", "Health: 4 X: 6 Y: 3\nXXXXXXXXXX\nX   X    X\nX   XXX  X\nX     H  X\nX   XX   X\nXX XXXXmXX\nX  \u221eXX   X\nX   XX   X\nXe\u221e  \u221e   X\nX   XX   X\nXX XXXX XX\nX   XX   X\nX   XX   X\nX      T X\nX   XX   X\nXX XXXX XX\nX   XX   X\nXb bXXT TX\nX   XXT TX\nXXXXXXXXXX\n", "Health: 4 X: 5 Y: 3\nXXXXXXXXXX\nX   X    X\nX   XXX  X\nX    H   X\nX   XX m X\nXX XXXX XX\nX  \u221eXX   X\nX   XX   X\nXe\u221e  \u221e   X\nX   XX   X\nXX XXXX XX\nX   XX   X\nX   XX   X\nX      T X\nX   XX   X\nXX XXXX XX\nX   XX   X\nXb bXXT TX\nX   XXT TX\nXXXXXXXXXX\n", "Health: 4 X: 4 Y: 3\nXXXXXXXXXX\nX   X    X\nX   XXX  X\nX   H  m X\nX   XX   X\nXX XXXX XX\nX  \u221eXX   X\nX   XX   X\nXe\u221e  \u221e   X\nX   XX   X\nXX XXXX XX\nX   XX   X\nX   XX   X\nX      T X\nX   XX   X\nXX XXXX XX\nX   XX   X\nXb bXXT TX\nX   XXT TX\nXXXXXXXXXX\n", "Health: 4 X: 3 Y: 3\nXXXXXXXXXX\nX   X    X\nX   XXX  X\nX  H  m  X\nX   XX   X\nXX XXXX XX\nX  \u221eXX   X\nX   XX   X\nXe\u221e  \u221e   X\nX   XX   X\nXX XXXX XX\nX   XX   X\nX   XX   X\nX      T X\nX   XX   X\nXX XXXX XX\nX   XX   X\nXb bXXT TX\nX   XXT TX\nXXXXXXXXXX\n", "Health: 4 X: 2 Y: 3\nXXXXXXXXXX\nX   X    X\nX   XXX  X\nX H  m   X\nX   XX   X\nXX XXXX XX\nX  \u221eXX   X\nX   XX   X\nXe\u221e  \u221e   X\nX   XX   X\nXX XXXX XX\nX   XX   X\nX   XX   X\nX      T X\nX   XX   X\nXX XXXX XX\nX   XX   X\nXb bXXT TX\nX   XXT TX\nXXXXXXXXXX\n", "Health: 4 X: 2 Y: 4\nXXXXXXXXXX\nX   X    X\nX   XXX  X\nX   m    X\nX H XX   X\nXX XXXX XX\nX  \u221eXX   X\nX   XX   X\nXe\u221e  \u221e   X\nX   XX   X\nXX XXXX XX\nX   XX   X\nX   XX   X\nX      T X\nX   XX   X\nXX XXXX XX\nX   XX   X\nXb bXXT TX\nX   XXT TX\nXXXXXXXXXX\n", "Health: 4 X: 2 Y: 5\nXXXXXXXXXX\nX   X    X\nX   XXX  X\nX  m     X\nX   XX   X\nXXHXXXX XX\nX  \u221eXX   X\nX   XX   X\nXe\u221e  \u221e   X\nX   XX   X\nXX XXXX XX\nX   XX   X\nX   XX   X\nX      T X\nX   XX   X\nXX XXXX XX\nX   XX   X\nXb bXXT TX\nX   XXT TX\nXXXXXXXXXX\n", "Health: 4 X: 2 Y: 6\nXXXXXXXXXX\nX   X    X\nX   XXX  X\nX m      X\nX   XX   X\nXX XXXX XX\nX  \u221eXX   X\nX   XX   X\nXe\u221e  \u221e   X\nX   XX   X\nXX XXXX XX\nX   XX   X\nX   XX   X\nX      T X\nX   XX   X\nXX XXXX XX\nX   XX   X\nXb bXXT TX\nX   XXT TX\nXXXXXXXXXX\n", "Health: 4 X: 2 Y: 7\nXXXXXXXXXX\nX   X    X\nX   XXX  X\nX        X\nX m XX   X\nXX XXXX XX\nX  \u221eXX   X\nX H XX   X\nXe\u221e  \u221e   X\nX   XX   X\nXX XXXX XX\nX   XX   X\nX   XX   X\nX      T X\nX   XX   X\nXX XXXX XX\nX   XX   X\nXb bXXT TX\nX   XXT TX\nXXXXXXXXXX\n", "Health: 4 X: 2 Y: 8\nXXXXXXXXXX\nX   X    X\nX   XXX  X\nX        X\nX   XX   X\nXXmXXXX XX\nX  \u221eXX   X\nX   XX   X\nXe\u221e  \u221e   X\nX   XX   X\nXX XXXX XX\nX   XX   X\nX   XX   X\nX      T X\nX   XX   X\nXX XXXX XX\nX   XX   X\nXb bXXT TX\nX   XXT TX\nXXXXXXXXXX\n", "Health: 4 X: 2 Y: 9\nXXXXXXXXXX\nX   X    X\nX   XXX  X\nX        X\nX   XX   X\nXX XXXX XX\nX  \u221eXX   X\nX   XX   X\nXe\u221e  \u221e   X\nX H XX   X\nXX XXXX XX\nX   XX   X\nX   XX   X\nX      T X\nX   XX   X\nXX XXXX XX\nX   XX   X\nXb bXXT TX\nX   XXT TX\nXXXXXXXXXX\n", "Health: 4 X: 3 Y: 9\nXXXXXXXXXX\nX   X    X\nX   XXX  X\nX        X\nX   XX   X\nXX XXXX XX\nX  \u221eXX   X\nX   XX   X\nXe\u221e  \u221e   X\nX  HXX   X\nXX XXXX XX\nX   XX   X\nX   XX   X\nX      T X\nX   XX   X\nXX XXXX XX\nX   XX   X\nXb bXXT TX\nX   XXT TX\nXXXXXXXXXX\n", "Health: 4 X: 3 Y: 8\nXXXXXXXXXX\nX   X    X\nX   XXX  X\nX        X\nX   XX   X\nXX XXXX XX\nX  \u221eXX   X\nX  mXX   X\nXe\u221eH \u221e   X\nX   XX   X\nXX XXXX XX\nX   XX   X\nX   XX   X\nX      T X\nX   XX   X\nXX XXXX XX\nX   XX   X\nXb bXXT TX\nX   XXT TX\nXXXXXXXXXX\n", "Health: 4 X: 4 Y: 8\nXXXXXXXXXX\nX   X    X\nX   XXX  X\nX        X\nX   XX   X\nXX XXXX XX\nX  \u221eXX   X\nX   XX   X\nXe\u221emH\u221e   X\nX   XX   X\nXX XXXX XX\nX   XX   X\nX   XX   X\nX      T X\nX   XX   X\nXX XXXX XX\nX   XX   X\nXb bXXT TX\nX   XXT TX\nXXXXXXXXXX\n", "Health: 4 X: 5 Y: 8\nXXXXXXXXXX\nX   X    X\nX   XXX  X\nX        X\nX   XX   X\nXX XXXX XX\nX  \u221eXX   X\nX   XX   X\nXe\u221e m\u221e   X\nX   XX   X\nXX XXXX XX\nX   XX   X\nX   XX   X\nX      T X\nX   XX   X\nXX XXXX XX\nX   XX   X\nXb bXXT TX\nX   XXT TX\nXXXXXXXXXX\n", "Health: 4 X: 5 Y: 8\nXXXXXXXXXX\nX   X    X\nX   XXX  X\nX        X\nX   XX   X\nXX XXXX XX\nX  \u221eXX   X\nX   XX   X\nXe\u221e m\u221e   X\nX   XX   X\nXX XXXX XX\nX   XX   X\nX   XX   X\nX      T X\nX   XX   X\nXX XXXX XX\nX   XX   X\nXb bXXT TX\nX   XXT TX\nXXXXXXXXXX\n", "Health: 4 X: 4 Y: 8\nXXXXXXXXXX\nX   X    X\nX   XXX  X\nX        X\nX   XX   X\nXX XXXX XX\nX  \u221eXX   X\nX   XX   X\nXe\u221e m\u221e   X\nX   XX   X\nXX XXXX XX\nX   XX   X\nX   XX   X\nX      T X\nX   XX   X\nXX XXXX XX\nX   XX   X\nXb bXXT TX\nX   XXT TX\nXXXXXXXXXX\n", "Health: 4 X: 5 Y: 8\nXXXXXXXXXX\nX   X    X\nX   XXX  X\nX        X\nX   XX   X\nXX XXXX XX\nX  \u221eXX   X\nX   XX   X\nXe\u221e m\u221e   X\nX   XX   X\nXX XXXX XX\nX   XX   X\nX   XX   X\nX      T X\nX   XX   X\nXX XXXX XX\nX   XX   X\nXb bXXT TX\nX   XXT TX\nXXXXXXXXXX\n", "Health: 4 X: 6 Y: 8\nXXXXXXXXXX\nX   X    X\nX   XXX  X\nX        X\nX   XX   X\nXX XXXX XX\nX  \u221eXX   X\nX   XX   X\nXe\u221e m\u221eH  X\nX   XX   X\nXX XXXX XX\nX   XX   X\nX   XX   X\nX      T X\nX   XX   X\nXX XXXX XX\nX   XX   X\nXb bXXT TX\nX   XXT TX\nXXXXXXXXXX\n", "Health: 4 X: 7 Y: 8\nXXXXXXXXXX\nX   X    X\nX   XXX  X\nX        X\nX   XX   X\nXX XXXX XX\nX  \u221eXX   X\nX   XX   X\nXe\u221e m\u221e H X\nX   XX   X\nXX XXXX XX\nX   XX   X\nX   XX   X\nX      T X\nX   XX   X\nXX XXXX XX\nX   XX   X\nXb bXXT TX\nX   XXT TX\nXXXXXXXXXX\n", "Health: 4 X: 7 Y: 9\nXXXXXXXXXX\nX   X    X\nX   XXX  X\nX        X\nX   XX   X\nXX XXXX XX\nX  \u221eXX   X\nX   XX   X\nXe\u221e  \u221e   X\nX   XX H X\nXX XXXX XX\nX   XX   X\nX   XX   X\nX      T X\nX   XX   X\nXX XXXX XX\nX   XX   X\nXb bXXT TX\nX   XXT TX\nXXXXXXXXXX\n", "Health: 4 X: 7 Y: 10\nXXXXXXXXXX\nX   X    X\nX   XXX  X\nX        X\nX   XX   X\nXX XXXX XX\nX  \u221eXX   X\nX   XX   X\nXe\u221e  \u221em  X\nX   XX   X\nXX XXXXHXX\nX   XX   X\nX   XX   X\nX      T X\nX   XX   X\nXX XXXX XX\nX   XX   X\nXb bXXT TX\nX   XXT TX\nXXXXXXXXXX\n", "Health: 4 X: 7 Y: 11\nXXXXXXXXXX\nX   X    X\nX   XXX  X\nX        X\nX   XX   X\nXX XXXX XX\nX  \u221eXX   X\nX   XX   X\nXe\u221e  \u221e m X\nX   XX   X\nXX XXXX XX\nX   XX H X\nX   XX   X\nX      T X\nX   XX   X\nXX XXXX XX\nX   XX   X\nXb bXXT TX\nX   XXT TX\nXXXXXXXXXX\n", "Health: 4 X: 7 Y: 12\nXXXXXXXXXX\nX   X    X\nX   XXX  X\nX        X\nX   XX   X\nXX XXXX XX\nX  \u221eXX   X\nX   XX   X\nXe\u221e  \u221e   X\nX   XX m X\nXX XXXX XX\nX   XX   X\nX   XX H X\nX      T X\nX   XX   X\nXX XXXX XX\nX   XX   X\nXb bXXT TX\nX   XXT TX\nXXXXXXXXXX\n", "Health: 4 X: 7 Y: 13\nXXXXXXXXXX\nX   X    X\nX   XXX  X\nX        X\nX   XX   X\nXX XXXX XX\nX  \u221eXX   X\nX   XX   X\nXe\u221e  \u221e   X\nX   XX   X\nXX XXXXmXX\nX   XX   X\nX   XX   X\nX        X\nX   XX   X\nXX XXXX XX\nX   XX   X\nXb bXXT TX\nX   XXT TX\nXXXXXXXXXX\n", "Health: 4 X: 7 Y: 14\nXXXXXXXXXX\nX   X    X\nX   XXX  X\nX        X\nX   XX   X\nXX XXXX XX\nX  \u221eXX   X\nX   XX   X\nXe\u221e  \u221e   X\nX   XX   X\nXX XXXX XX\nX   XX m X\nX   XX   X\nX        X\nX   XX H X\nXX XXXX XX\nX   XX   X\nXb bXXT TX\nX   XXT TX\nXXXXXXXXXX\n", "Health: 4 X: 7 Y: 15\nXXXXXXXXXX\nX   X    X\nX   XXX  X\nX        X\nX   XX   X\nXX XXXX XX\nX  \u221eXX   X\nX   XX   X\nXe\u221e  \u221e   X\nX   XX   X\nXX XXXX XX\nX   XX   X\nX   XX m X\nX        X\nX   XX   X\nXX XXXXHXX\nX   XX   X\nXb bXXT TX\nX   XXT TX\nXXXXXXXXXX\n", "Health: 4 X: 7 Y: 16\nXXXXXXXXXX\nX   X    X\nX   XXX  X\nX        X\nX   XX   X\nXX XXXX XX\nX  \u221eXX   X\nX   XX   X\nXe\u221e  \u221e   X\nX   XX   X\nXX XXXX XX\nX   XX   X\nX   XX   X\nX        X\nX   XX   X\nXX XXXX XX\nX   XX H X\nXb bXXT TX\nX   XXT TX\nXXXXXXXXXX\n", "Health: 4 X: 7 Y: 17\nXXXXXXXXXX\nX   X    X\nX   XXX  X\nX        X\nX   XX   X\nXX XXXX XX\nX  \u221eXX   X\nX   XX   X\nXe\u221e  \u221e   X\nX   XX   X\nXX XXXX XX\nX   XX   X\nX   XX   X\nX        X\nX   XX m X\nXX XXXX XX\nX   XX   X\nXb bXXTHTX\nX   XXT TX\nXXXXXXXXXX\n", "Health: 4 X: 8 Y: 17\nXXXXXXXXXX\nX   X    X\nX   XXX  X\nX        X\nX   XX   X\nXX XXXX XX\nX  \u221eXX   X\nX   XX   X\nXe\u221e  \u221e   X\nX   XX   X\nXX XXXX XX\nX   XX   X\nX   XX   X\nX        X\nX   XX   X\nXX XXXXmXX\nX   XX   X\nXb bXXT  X\nX   XXT TX\nXXXXXXXXXX\n", "Health: 4 X: 8 Y: 18\nXXXXXXXXXX\nX   X    X\nX   XXX  X\nX        X\nX   XX   X\nXX XXXX XX\nX  \u221eXX   X\nX   XX   X\nXe\u221e  \u221e   X\nX   XX   X\nXX XXXX XX\nX   XX   X\nX   XX   X\nX        X\nX   XX   X\nXX XXXX XX\nX   XX m X\nXb bXXT  X\nX   XXT  X\nXXXXXXXXXX\n", "Health: 4 X: 7 Y: 18\nXXXXXXXXXX\nX   X    X\nX   XXX  X\nX        X\nX   XX   X\nXX XXXX XX\nX  \u221eXX   X\nX   XX   X\nXe\u221e  \u221e   X\nX   XX   X\nXX XXXX XX\nX   XX   X\nX   XX   X\nX        X\nX   XX   X\nXX XXXX XX\nX   XX   X\nXb bXXTm X\nX   XXTH X\nXXXXXXXXXX\n", "Health: 4 X: 7 Y: 18\nXXXXXXXXXX\nX   X    X\nX   XXX  X\nX        X\nX   XX   X\nXX XXXX XX\nX  \u221eXX   X\nX   XX   X\nXe\u221e  \u221e   X\nX   XX   X\nXX XXXX XX\nX   XX   X\nX   XX   X\nX        X\nX   XX   X\nXX XXXX XX\nX   XX   X\nXb bXXTm X\nX   XXTH X\nXXXXXXXXXX\n", "Health: 4 X: 7 Y: 17\nXXXXXXXXXX\nX   X    X\nX   XXX  X\nX        X\nX   XX   X\nXX XXXX XX\nX  \u221eXX   X\nX   XX   X\nXe\u221e  \u221e   X\nX   XX   X\nXX XXXX XX\nX   XX   X\nX   XX   X\nX        X\nX   XX   X\nXX XXXX XX\nX   XX   X\nXb bXXTm X\nX   XXT  X\nXXXXXXXXXX\n", "Health: 4 X: 6 Y: 17\nXXXXXXXXXX\nX   X    X\nX   XXX  X\nX        X\nX   XX   X\nXX XXXX XX\nX  \u221eXX   X\nX   XX   X\nXe\u221e  \u221e   X\nX   XX   X\nXX XXXX XX\nX   XX   X\nX   XX   X\nX        X\nX   XX   X\nXX XXXX XX\nX   XX   X\nXb bXX m X\nX   XXT  X\nXXXXXXXXXX\n", "Health: 4 X: 6 Y: 18\nXXXXXXXXXX\nX   X    X\nX   XXX  X\nX        X\nX   XX   X\nXX XXXX XX\nX  \u221eXX   X\nX   XX   X\nXe\u221e  \u221e   X\nX   XX   X\nXX XXXX XX\nX   XX   X\nX   XX   X\nX        X\nX   XX   X\nXX XXXX XX\nX   XX   X\nXb bXX m X\nX   XX   X\nXXXXXXXXXX\n", "Health: 4 X: 7 Y: 18\nXXXXXXXXXX\nX   X    X\nX   XXX  X\nX        X\nX   XX   X\nXX XXXX XX\nX  \u221eXX   X\nX   XX   X\nXe\u221e  \u221e   X\nX   XX   X\nXX XXXX XX\nX   XX   X\nX   XX   X\nX        X\nX   XX   X\nXX XXXX XX\nX   XX   X\nXb bXX m X\nX   XX H X\nXXXXXXXXXX\n", "Health: 3 X: 7 Y: 17\nXXXXXXXXXX\nX   X    X\nX   XXX  X\nX        X\nX   XX   X\nXX XXXX XX\nX  \u221eXX   X\nX   XX   X\nXe\u221e  \u221e   X\nX   XX   X\nXX XXXX XX\nX   XX   X\nX   XX   X\nX        X\nX   XX   X\nXX XXXX XX\nX   XX   X\nXb bXX m X\nX   XX   X\nXXXXXXXXXX\n", "Health: 3 X: 7 Y: 16\nXXXXXXXXXX\nX   X    X\nX   XXX  X\nX        X\nX   XX   X\nXX XXXX XX\nX  \u221eXX   X\nX   XX   X\nXe\u221e  \u221e   X\nX   XX   X\nXX XXXX XX\nX   XX   X\nX   XX   X\nX        X\nX   XX   X\nXX XXXX XX\nX   XX H X\nXb bXX m X\nX   XX   X\nXXXXXXXXXX\n", "Health: 3 X: 7 Y: 15\nXXXXXXXXXX\nX   X    X\nX   XXX  X\nX        X\nX   XX   X\nXX XXXX XX\nX  \u221eXX   X\nX   XX   X\nXe\u221e  \u221e   X\nX   XX   X\nXX XXXX XX\nX   XX   X\nX   XX   X\nX        X\nX   XX   X\nXX XXXXHXX\nX   XX   X\nXb bXX m X\nX   XX   X\nXXXXXXXXXX\n", "Health: 3 X: 7 Y: 14\nXXXXXXXXXX\nX   X    X\nX   XXX  X\nX        X\nX   XX   X\nXX XXXX XX\nX  \u221eXX   X\nX   XX   X\nXe\u221e  \u221e   X\nX   XX   X\nXX XXXX XX\nX   XX   X\nX   XX   X\nX        X\nX   XX H X\nXX XXXX XX\nX   XX   X\nXb bXX m X\nX   XX   X\nXXXXXXXXXX\n", "Health: 3 X: 7 Y: 13\nXXXXXXXXXX\nX   X    X\nX   XXX  X\nX        X\nX   XX   X\nXX XXXX XX\nX  \u221eXX   X\nX   XX   X\nXe\u221e  \u221e   X\nX   XX   X\nXX XXXX XX\nX   XX   X\nX   XX   X\nX        X\nX   XX   X\nXX XXXX XX\nX   XX   X\nXb bXX m X\nX   XX   X\nXXXXXXXXXX\n", "Health: 3 X: 7 Y: 12\nXXXXXXXXXX\nX   X    X\nX   XXX  X\nX        X\nX   XX   X\nXX XXXX XX\nX  \u221eXX   X\nX   XX   X\nXe\u221e  \u221e   X\nX   XX   X\nXX XXXX XX\nX   XX   X\nX   XX H X\nX        X\nX   XX   X\nXX XXXX XX\nX   XX m X\nXb bXX   X\nX   XX   X\nXXXXXXXXXX\n", "Health: 3 X: 7 Y: 11\nXXXXXXXXXX\nX   X    X\nX   XXX  X\nX        X\nX   XX   X\nXX XXXX XX\nX  \u221eXX   X\nX   XX   X\nXe\u221e  \u221e   X\nX   XX   X\nXX XXXX XX\nX   XX H X\nX   XX   X\nX        X\nX   XX   X\nXX XXXXmXX\nX   XX   X\nXb bXX   X\nX   XX   X\nXXXXXXXXXX\n", "Health: 3 X: 7 Y: 10\nXXXXXXXXXX\nX   X    X\nX   XXX  X\nX        X\nX   XX   X\nXX XXXX XX\nX  \u221eXX   X\nX   XX   X\nXe\u221e  \u221e   X\nX   XX   X\nXX XXXXHXX\nX   XX   X\nX   XX   X\nX        X\nX   XX m X\nXX XXXX XX\nX   XX   X\nXb bXX   X\nX   XX   X\nXXXXXXXXXX\n", "Health: 3 X: 7 Y: 9\nXXXXXXXXXX\nX   X    X\nX   XXX  X\nX        X\nX   XX   X\nXX XXXX XX\nX  \u221eXX   X\nX   XX   X\nXe\u221e  \u221e   X\nX   XX H X\nXX XXXX XX\nX   XX   X\nX   XX   X\nX        X\nX   XX   X\nXX XXXX XX\nX   XX   X\nXb bXX   X\nX   XX   X\nXXXXXXXXXX\n", "Health: 3 X: 7 Y: 8\nXXXXXXXXXX\nX   X    X\nX   XXX  X\nX        X\nX   XX   X\nXX XXXX XX\nX  \u221eXX   X\nX   XX   X\nXe\u221e  \u221e H X\nX   XX   X\nXX XXXX XX\nX   XX   X\nX   XX m X\nX        X\nX   XX   X\nXX XXXX XX\nX   XX   X\nXb bXX   X\nX   XX   X\nXXXXXXXXXX\n", "Health: 3 X: 6 Y: 8\nXXXXXXXXXX\nX   X    X\nX   XXX  X\nX        X\nX   XX   X\nXX XXXX XX\nX  \u221eXX   X\nX   XX   X\nXe\u221e  \u221eH  X\nX   XX   X\nXX XXXX XX\nX   XX m X\nX   XX   X\nX        X\nX   XX   X\nXX XXXX XX\nX   XX   X\nXb bXX   X\nX   XX   X\nXXXXXXXXXX\n", "Health: 3 X: 5 Y: 8\nXXXXXXXXXX\nX   X    X\nX   XXX  X\nX        X\nX   XX   X\nXX XXXX XX\nX  \u221eXX   X\nX   XX   X\nXe\u221e  \u221e   X\nX   XX   X\nXX XXXXmXX\nX   XX   X\nX   XX   X\nX        X\nX   XX   X\nXX XXXX XX\nX   XX   X\nXb bXX   X\nX   XX   X\nXXXXXXXXXX\n", "Health: 3 X: 4 Y: 8\nXXXXXXXXXX\nX   X    X\nX   XXX  X\nX        X\nX   XX   X\nXX XXXX XX\nX  \u221eXX   X\nX   XX   X\nXe\u221e H\u221e   X\nX   XX m X\nXX XXXX XX\nX   XX   X\nX   XX   X\nX        X\nX   XX   X\nXX XXXX XX\nX   XX   X\nXb bXX   X\nX   XX   X\nXXXXXXXXXX\n", "Health: 3 X: 3 Y: 8\nXXXXXXXXXX\nX   X    X\nX   XXX  X\nX        X\nX   XX   X\nXX XXXX XX\nX  \u221eXX   X\nX   XX   X\nXe\u221eH \u221e m X\nX   XX   X\nXX XXXX XX\nX   XX   X\nX   XX   X\nX        X\nX   XX   X\nXX XXXX XX\nX   XX   X\nXb bXX   X\nX   XX   X\nXXXXXXXXXX\n", "Health: 3 X: 2 Y: 8\nXXXXXXXXXX\nX   X    X\nX   XXX  X\nX        X\nX   XX   X\nXX XXXX XX\nX  \u221eXX   X\nX   XX   X\nXe\u221e  \u221em  X\nX   XX   X\nXX XXXX XX\nX   XX   X\nX   XX   X\nX        X\nX   XX   X\nXX XXXX XX\nX   XX   X\nXb bXX   X\nX   XX   X\nXXXXXXXXXX\n", "Health: 3 X: 1 Y: 8\nXXXXXXXXXX\nX   X    X\nX   XXX  X\nX        X\nX   XX   X\nXX XXXX XX\nX  \u221eXX   X\nX   XX   X\nXe\u221e  \u221e   X\nX   XX   X\nXX XXXX XX\nX   XX   X\nX   XX   X\nX        X\nX   XX   X\nXX XXXX XX\nX   XX   X\nXb bXX   X\nX   XX   X\nXXXXXXXXXX\n"], "map_number": 101}, {"mechanics": [{"timestep": 1, "mechanic": "JavelinThrow"}, {"timestep": 6, "mechanic": "JavelinThrow"}, {"timestep": 9, "mechanic": "MinitaurHit"}, {"timestep": 12, "mechanic": "JavelinThrow"}, {"timestep": 13, "mechanic": "MinitaurHit"}, {"timestep": 19, "mechanic": "UsePortal"}, {"timestep": 23, "mechanic": "JavelinThrow"}, {"timestep": 24, "mechanic": "CollectTreasure"}, {"timestep": 24, "mechanic": "GoblinRangedHit"}, {"timestep": 25, "mechanic": "GoblinRangedHit"}, {"timestep": 26, "mechanic": "GoblinRangedHit"}, {"timestep": 29, "mechanic": "CollectTreasure"}, {"timestep": 35, "mechanic": "CollectTreasure"}, {"timestep": 38, "mechanic": "CollectPotion"}, {"timestep": 54, "mechanic": "CollectTreasure"}, {"timestep": 57, "mechanic": "CollectPotion"}, {"timestep": 68, "mechanic": "TriggerTrap"}, {"timestep": 70, "mechanic": "CollectTreasure"}, {"timestep": 71, "mechanic": "CollectTreasure"}, {"timestep": 72, "mechanic": "CollectTreasure"}, {"timestep": 73, "mechanic": "CollectTreasure"}, {"timestep": 80, "mechanic": "MinitaurHit"}, {"timestep": 80, "mechanic": "TriggerTrap"}, {"timestep": 94, "mechanic": "ReachStairs"}], "frequencies": {"JavelinThrow": 4, "MinitaurHit": 3, "UsePortal": 1, "CollectTreasure": 8, "GoblinRangedHit": 3, "CollectPotion": 2, "TriggerTrap": 2, "ReachStairs": 1}, "levelReport": {"utilityGained": 0.0, "exitUtility": 1.0, "runnerUtility": 0.050000000000000044, "loitererUtility": 95.0, "completionistUtility": 0.922222222222222, "monsterKillerUtility": 0.7666666666666666, "treasureCollectorUtility": 1.0, "turnsTaken": 95, "health": 10, "healthLost": 4, "alive": true, "javelinsThrown": 4, "monsterKills": 4, "minitaurKnockouts": 5, "treasuresCollected": 8, "potionsTaken": 2, "totalMonsters": 7, "totalTreasures": 8, "totalPotions": 2, "timeTaken": 0.0}, "positions": [{"X": 7, "Y": 3}, {"X": 7, "Y": 3}, {"X": 6, "Y": 3}, {"X": 5, "Y": 3}, {"X": 4, "Y": 3}, {"X": 5, "Y": 3}, {"X": 5, "Y": 3}, {"X": 6, "Y": 3}, {"X": 7, "Y": 3}, {"X": 8, "Y": 3}, {"X": 8, "Y": 2}, {"X": 8, "Y": 1}, {"X": 8, "Y": 1}, {"X": 8, "Y": 2}, {"X": 8, "Y": 1}, {"X": 7, "Y": 1}, {"X": 6, "Y": 1}, {"X": 5, "Y": 1}, {"X": 4, "Y": 1}, {"X": 1, "Y": 17}, {"X": 2, "Y": 17}, {"X": 3, "Y": 17}, {"X": 4, "Y": 17}, {"X": 4, "Y": 17}, {"X": 4, "Y": 16}, {"X": 4, "Y": 15}, {"X": 4, "Y": 14}, {"X": 5, "Y": 14}, {"X": 5, "Y": 15}, {"X": 5, "Y": 16}, {"X": 6, "Y": 16}, {"X": 7, "Y": 16}, {"X": 8, "Y": 16}, {"X": 8, "Y": 15}, {"X": 8, "Y": 14}, {"X": 8, "Y": 13}, {"X": 8, "Y": 12}, {"X": 8, "Y": 11}, {"X": 7, "Y": 11}, {"X": 8, "Y": 11}, {"X": 8, "Y": 12}, {"X": 8, "Y": 13}, {"X": 8, "Y": 14}, {"X": 8, "Y": 15}, {"X": 8, "Y": 16}, {"X": 7, "Y": 16}, {"X": 6, "Y": 16}, {"X": 5, "Y": 16}, {"X": 4, "Y": 16}, {"X": 3, "Y": 16}, {"X": 2, "Y": 16}, {"X": 1, "Y": 16}, {"X": 1, "Y": 15}, {"X": 1, "Y": 14}, {"X": 1, "Y": 13}, {"X": 1, "Y": 12}, {"X": 1, "Y": 11}, {"X": 2, "Y": 11}, {"X": 3, "Y": 11}, {"X": 4, "Y": 11}, {"X": 5, "Y": 11}, {"X": 6, "Y": 11}, {"X": 7, "Y": 11}, {"X": 8, "Y": 11}, {"X": 8, "Y": 10}, {"X": 8, "Y": 9}, {"X": 8, "Y": 8}, {"X": 8, "Y": 7}, {"X": 8, "Y": 6}, {"X": 7, "Y": 6}, {"X": 6, "Y": 6}, {"X": 6, "Y": 7}, {"X": 6, "Y": 8}, {"X": 6, "Y": 9}, {"X": 6, "Y": 8}, {"X": 6, "Y": 7}, {"X": 6, "Y": 6}, {"X": 6, "Y": 7}, {"X": 6, "Y": 6}, {"X": 7, "Y": 6}, {"X": 8, "Y": 6}, {"X": 8, "Y": 7}, {"X": 8, "Y": 8}, {"X": 8, "Y": 9}, {"X": 8, "Y": 10}, {"X": 8, "Y": 11}, {"X": 8, "Y": 12}, {"X": 8, "Y": 13}, {"X": 8, "Y": 14}, {"X": 8, "Y": 15}, {"X": 8, "Y": 16}, {"X": 8, "Y": 17}, {"X": 7, "Y": 17}, {"X": 6, "Y": 17}, {"X": 5, "Y": 17}], "levelStates": ["Health: 10 X: 7 Y: 3\nXXXXXXXXXX\nXXXT m   X\nXXXXXXXX X\nX     bH X\nX XX XXXXX\nX XX XXXXX\nX MX XT tX\nX XX XTX X\nX XX XTX X\nX MX XTX X\nX XX XXX X\nX P o  P X\nX XXXXXX X\nXTX RR XTX\nX X    X X\nX XX  XX X\nX   TT   X\nXT   e   X\nXXXXXXXXXX\n", "Health: 10 X: 7 Y: 3\nXXXXXXXXXX\nXXXT  m  X\nXXXXXXXX X\nX     \u221eH X\nX XX XXXXX\nX XX XXXXX\nX MX XT tX\nX XX XTX X\nX XX XTX X\nX MX XTX X\nX XX XXX X\nX P o  P X\nX XXXXXX X\nXTX RR XTX\nX X    X X\nX XX  XX X\nX   TT   X\nXT   e   X\nXXXXXXXXXX\n", "Health: 10 X: 6 Y: 3\nXXXXXXXXXX\nXXXT   m X\nXXXXXXXX X\nX     \u221e  X\nX XX XXXXX\nX XX XXXXX\nX MX XT tX\nX XX XTX X\nX XX XTX X\nX MX XTX X\nX XX XXX X\nX P o  P X\nX XXXXXX X\nXTX RR XTX\nX X    X X\nX XX  XX X\nX   TT   X\nXT   e   X\nXXXXXXXXXX\n", "Health: 10 X: 5 Y: 3\nXXXXXXXXXX\nXXXT    mX\nXXXXXXXX X\nX    H\u221e  X\nX XX XXXXX\nX XX XXXXX\nX MX XT tX\nX XX XTX X\nX XX XTX X\nX MX XTX X\nX XX XXX X\nX P o  P X\nX XXXXXX X\nXTX RR XTX\nX X    X X\nX XX  XX X\nX   TT   X\nXT   e   X\nXXXXXXXXXX\n", "Health: 10 X: 4 Y: 3\nXXXXXXXXXX\nXXXT     X\nXXXXXXXXmX\nX   H \u221e  X\nX XX XXXXX\nX XX XXXXX\nX MX XT tX\nX XX XTX X\nX XX XTX X\nX MX XTX X\nX XXoXXX X\nX P    P X\nX XXXXXX X\nXTX RR XTX\nX X    X X\nX XX  XX X\nX   TT   X\nXT   e   X\nXXXXXXXXXX\n", "Health: 10 X: 5 Y: 3\nXXXXXXXXXX\nXXXT     X\nXXXXXXXX X\nX    H\u221e mX\nX XX XXXXX\nX XX XXXXX\nX MX XT tX\nX XX XTX X\nX XX XTX X\nX MX XTX X\nX XXoXXX X\nX P    P X\nX XXXXXX X\nXTX RR XTX\nX X    X X\nX XX  XX X\nX   TT   X\nXT   e   X\nXXXXXXXXXX\n", "Health: 10 X: 5 Y: 3\nXXXXXXXXXX\nXXXT     X\nXXXXXXXX X\nX    H\u221e mX\nX XX XXXXX\nX XX XXXXX\nX MX XT tX\nX XX XTX X\nX XX XTX X\nX MX XTX X\nX XXoXXX X\nX P    P X\nX XXXXXX X\nXTX RR XTX\nX X    X X\nX XX  XX X\nX   TT   X\nXT   e   X\nXXXXXXXXXX\n", "Health: 10 X: 6 Y: 3\nXXXXXXXXXX\nXXXT     X\nXXXXXXXX X\nX     \u221e mX\nX XX XXXXX\nX XX XXXXX\nX MX XT tX\nX XX XTX X\nX XX XTX X\nX MX XTX X\nX XXoXXX X\nX P    P X\nX XXXXXX X\nXTX RR XTX\nX X    X X\nX XX  XX X\nX   TT   X\nXT   e   X\nXXXXXXXXXX\n", "Health: 10 X: 7 Y: 3\nXXXXXXXXXX\nXXXT     X\nXXXXXXXX X\nX     \u221eHmX\nX XX XXXXX\nX XX XXXXX\nX MX XT tX\nX XX XTX X\nX XX XTX X\nX MX XTX X\nX XXoXXX X\nX P    P X\nX XXXXXX X\nXTX RR XTX\nX X    X X\nX XX  XX X\nX   TT   X\nXT   e   X\nXXXXXXXXXX\n", "Health: 10 X: 8 Y: 3\nXXXXXXXXXX\nXXXT     X\nXXXXXXXX X\nX     \u221e mX\nX XX XXXXX\nX XX XXXXX\nX MX XT tX\nX XX XTX X\nX XX XTX X\nX MX XTX X\nX XXoXXX X\nX P    P X\nX XXXXXX X\nXTX RR XTX\nX X    X X\nX XX  XX X\nX   TT   X\nXT   e   X\nXXXXXXXXXX\n", "Health: 10 X: 8 Y: 2\nXXXXXXXXXX\nXXXT     X\nXXXXXXXXHX\nX     \u221e mX\nX XX XXXXX\nX XX XXXXX\nX MX XT tX\nX XX XTX X\nX XX XTX X\nX MX XTX X\nX XXoXXX X\nX P    P X\nX XXXXXX X\nXTX RR XTX\nX X    X X\nX XX  XX X\nX   TT   X\nXT   e   X\nXXXXXXXXXX\n", "Health: 10 X: 8 Y: 1\nXXXXXXXXXX\nXXXT    HX\nXXXXXXXXmX\nX     \u221e  X\nX XX XXXXX\nX XX XXXXX\nX MX XT tX\nX XX XTX X\nX XX XTX X\nX MX XTX X\nX XXoXXX X\nX P    P X\nX XXXXXX X\nXTX RR XTX\nX X    X X\nX XX  XX X\nX   TT   X\nXT   e   X\nXXXXXXXXXX\n", "Health: 10 X: 8 Y: 1\nXXXXXXXXXX\nXXXT    HX\nXXXXXXXXmX\nX     \u221e  X\nX XX XXXXX\nX XX XXXXX\nX MX XT tX\nX XX XTX X\nX XX XTX X\nX MX XTX X\nX XXoXXX X\nX P    P X\nX XXXXXX X\nXTX RR XTX\nX X    X X\nX XX  XX X\nX   TT   X\nXT   e   X\nXXXXXXXXXX\n", "Health: 10 X: 8 Y: 2\nXXXXXXXXXX\nXXXT     X\nXXXXXXXXmX\nX     \u221e  X\nX XX XXXXX\nX XX XXXXX\nX MX XT tX\nX XX XTX X\nX XX XTX X\nX MX XTX X\nX XXoXXX X\nX P    P X\nX XXXXXX X\nXTX RR XTX\nX X    X X\nX XX  XX X\nX   TT   X\nXT   e   X\nXXXXXXXXXX\n", "Health: 10 X: 8 Y: 1\nXXXXXXXXXX\nXXXT    HX\nXXXXXXXXmX\nX     \u221e  X\nX XX XXXXX\nX XX XXXXX\nX MX XT tX\nX XX XTX X\nX XX XTX X\nX MX XTX X\nX XXoXXX X\nX P    P X\nX XXXXXX X\nXTX RR XTX\nX X    X X\nX XX  XX X\nX   TT   X\nXT   e   X\nXXXXXXXXXX\n", "Health: 10 X: 7 Y: 1\nXXXXXXXXXX\nXXXT   H X\nXXXXXXXXmX\nX     \u221e  X\nX XX XXXXX\nX XX XXXXX\nX MX XT tX\nX XX XTX X\nX XX XTX X\nX MX XTX X\nX XXoXXX X\nX P    P X\nX XXXXXX X\nXTX RR XTX\nX X    X X\nX XX  XX X\nX   TT   X\nXT   e   X\nXXXXXXXXXX\n", "Health: 10 X: 6 Y: 1\nXXXXXXXXXX\nXXXT  H  X\nXXXXXXXXmX\nX     \u221e  X\nX XX XXXXX\nX XX XXXXX\nX MX XT tX\nX XX XTX X\nX XX XTX X\nX MX XTX X\nX XXoXXX X\nX P    P X\nX XXXXXX X\nXTX RR XTX\nX X    X X\nX XX  XX X\nX   TT   X\nXT   e   X\nXXXXXXXXXX\n", "Health: 10 X: 5 Y: 1\nXXXXXXXXXX\nXXXT H  mX\nXXXXXXXX X\nX     \u221e  X\nX XX XXXXX\nX XX XXXXX\nX MX XT tX\nX XX XTX X\nX XX XTX X\nX MX XTX X\nX XXoXXX X\nX P    P X\nX XXXXXX X\nXTX RR XTX\nX X    X X\nX XX  XX X\nX   TT   X\nXT   e   X\nXXXXXXXXXX\n", "Health: 10 X: 4 Y: 1\nXXXXXXXXXX\nXXXTH  m X\nXXXXXXXX X\nX     \u221e  X\nX XX XXXXX\nX XX XXXXX\nX MX XT tX\nX XX XTX X\nX XX XTX X\nX MX XTX X\nX XXoXXX X\nX P    P X\nX XXXXXX X\nXTX RR XTX\nX X    X X\nX XX  XX X\nX   TT   X\nXT   e   X\nXXXXXXXXXX\n", "Health: 10 X: 1 Y: 17\nXXXXXXXXXX\nXXXT    mX\nXXXXXXXX X\nX     \u221e  X\nX XX XXXXX\nX XX XXXXX\nX MX XT tX\nX XX XTX X\nX XX XTX X\nX MX XTX X\nX XXoXXX X\nX P    P X\nX XXXXXX X\nXTX RR XTX\nX X    X X\nX XX  XX X\nX   TT   X\nXT   e   X\nXXXXXXXXXX\n", "Health: 10 X: 2 Y: 17\nXXXXXXXXXX\nXXXT     X\nXXXXXXXXmX\nX     \u221e  X\nX XX XXXXX\nX XX XXXXX\nX MX XT tX\nX XX XTX X\nX XX XTX X\nX MX XTX X\nX XXoXXX X\nX P    P X\nX XXXXXX X\nXTX RR XTX\nX X    X X\nX XX  XX X\nX   TT   X\nXTH  e   X\nXXXXXXXXXX\n", "Health: 10 X: 3 Y: 17\nXXXXXXXXXX\nXXXT     X\nXXXXXXXX X\nX     \u221e mX\nX XX XXXXX\nX XX XXXXX\nX MX XT tX\nX XX XTX X\nX XX XTX X\nX MX XTX X\nX XXoXXX X\nX P    P X\nX XXXXXX X\nXTX RR XTX\nX X    X X\nX XX  XX X\nX   TT   X\nXT H e   X\nXXXXXXXXXX\n", "Health: 10 X: 4 Y: 17\nXXXXXXXXXX\nXXXT     X\nXXXXXXXX X\nX     \u221em X\nX XX XXXXX\nX XX XXXXX\nX MX XT tX\nX XX XTX X\nX XX XTX X\nX MX XTX X\nX XXoXXX X\nX P    P X\nX XXXXXX X\nXTX R  XTX\nX X R  X X\nX XX  XX X\nX   TT   X\nXT  He   X\nXXXXXXXXXX\n", "Health: 10 X: 4 Y: 17\nXXXXXXXXXX\nXXXT     X\nXXXXXXXX X\nX     \u221e  X\nX XX XXXXX\nX XX XXXXX\nX MX XT tX\nX XX XTX X\nX XX XTX X\nX MX XTX X\nX XXoXXX X\nX P    P X\nX XXXXXX X\nXTX    XTX\nX X R  X X\nX XX  XX X\nX   TT   X\nXT  He   X\nXXXXXXXXXX\n", "Health: 9 X: 4 Y: 16\nXXXXXXXXXX\nXXXT     X\nXXXXXXXX X\nX    m\u221e  X\nX XX XXXXX\nX XX XXXXX\nX MX XT tX\nX XX XTX X\nX XX XTX X\nX MX XTX X\nX XXoXXX X\nX P    P X\nX XXXXXX X\nXTX    XTX\nX X R  X X\nX XX  XX X\nX    T   X\nXT   e   X\nXXXXXXXXXX\n", "Health: 8 X: 4 Y: 15\nXXXXXXXXXX\nXXXT     X\nXXXXXXXX X\nX   m \u221e  X\nX XX XXXXX\nX XX XXXXX\nX MX XT tX\nX XX XTX X\nX XX XTX X\nX MX XTX X\nX XXoXXX X\nX P    P X\nX XXXXXX X\nXTX    XTX\nX X R  X X\nX XXH XX X\nX    T   X\nXT   e   X\nXXXXXXXXXX\n", "Health: 8 X: 4 Y: 14\nXXXXXXXXXX\nXXXT     X\nXXXXXXXX X\nX     \u221e  X\nX XXmXXXXX\nX XX XXXXX\nX MX XT tX\nX XX XTX X\nX XX XTX X\nX MX XTX X\nX XXoXXX X\nX P    P X\nX XXXXXX X\nXTX    XTX\nX X \u221e  X X\nX XX  XX X\nX    T   X\nXT   e   X\nXXXXXXXXXX\n", "Health: 8 X: 5 Y: 14\nXXXXXXXXXX\nXXXT     X\nXXXXXXXX X\nX     \u221e  X\nX XX XXXXX\nX XXmXXXXX\nX MX XT tX\nX XX XTX X\nX XX XTX X\nX MX XTX X\nX XXoXXX X\nX P    P X\nX XXXXXX X\nXTX    XTX\nX X \u221eH X X\nX XX  XX X\nX    T   X\nXT   e   X\nXXXXXXXXXX\n", "Health: 8 X: 5 Y: 15\nXXXXXXXXXX\nXXXT     X\nXXXXXXXX X\nX     \u221e  X\nX XX XXXXX\nX XX XXXXX\nX MXmXT tX\nX XX XTX X\nX XX XTX X\nX MX XTX X\nX XXoXXX X\nX P    P X\nX XXXXXX X\nXTX    XTX\nX X \u221e  X X\nX XX HXX X\nX    T   X\nXT   e   X\nXXXXXXXXXX\n", "Health: 8 X: 5 Y: 16\nXXXXXXXXXX\nXXXT     X\nXXXXXXXX X\nX     \u221e  X\nX XX XXXXX\nX XX XXXXX\nX MX XT tX\nX XXmXTX X\nX XX XTX X\nX MX XTX X\nX XXoXXX X\nX P    P X\nX XXXXXX X\nXTX    XTX\nX X \u221e  X X\nX XX  XX X\nX        X\nXT   e   X\nXXXXXXXXXX\n", "Health: 8 X: 6 Y: 16\nXXXXXXXXXX\nXXXT     X\nXXXXXXXX X\nX     \u221e  X\nX XX XXXXX\nX XX XXXXX\nX MX XT tX\nX XX XTX X\nX XXmXTX X\nX MX XTX X\nX XXoXXX X\nX P    P X\nX XXXXXX X\nXTX    XTX\nX X \u221e  X X\nX XX  XX X\nX     H  X\nXT   e   X\nXXXXXXXXXX\n", "Health: 8 X: 7 Y: 16\nXXXXXXXXXX\nXXXT     X\nXXXXXXXX X\nX     \u221e  X\nX XX XXXXX\nX XX XXXXX\nX MX XT tX\nX XX XTX X\nX XX XTX X\nX MXmXTX X\nX XXoXXX X\nX P    P X\nX XXXXXX X\nXTX    XTX\nX X \u221e  X X\nX XX  XX X\nX      H X\nXT   e   X\nXXXXXXXXXX\n", "Health: 8 X: 8 Y: 16\nXXXXXXXXXX\nXXXT     X\nXXXXXXXX X\nX     \u221e  X\nX XX XXXXX\nX XX XXXXX\nX MX XT tX\nX XX XTX X\nX XX XTX X\nX MXmXTX X\nX XXoXXX X\nX P    P X\nX XXXXXX X\nXTX    XTX\nX X \u221e  X X\nX XX  XX X\nX       HX\nXT   e   X\nXXXXXXXXXX\n", "Health: 8 X: 8 Y: 15\nXXXXXXXXXX\nXXXT     X\nXXXXXXXX X\nX     \u221e  X\nX XX XXXXX\nX XX XXXXX\nX MX XT tX\nX XX XTX X\nX XX XTX X\nX MXmXTX X\nX XXoXXX X\nX P    P X\nX XXXXXX X\nXTX    XTX\nX X \u221e  X X\nX XX  XXHX\nX        X\nXT   e   X\nXXXXXXXXXX\n", "Health: 8 X: 8 Y: 14\nXXXXXXXXXX\nXXXT     X\nXXXXXXXX X\nX     \u221e  X\nX XX XXXXX\nX XX XXXXX\nX MX XT tX\nX XX XTX X\nX XX XTX X\nX MXmXTX X\nX XXoXXX X\nX P    P X\nX XXXXXX X\nXTX    XTX\nX X \u221e  XHX\nX XX  XX X\nX        X\nXT   e   X\nXXXXXXXXXX\n", "Health: 8 X: 8 Y: 13\nXXXXXXXXXX\nXXXT     X\nXXXXXXXX X\nX     \u221e  X\nX XX XXXXX\nX XX XXXXX\nX MX XT tX\nX XX XTX X\nX XX XTX X\nX MXmXTX X\nX XXoXXX X\nX P    P X\nX XXXXXX X\nXTX    X X\nX X \u221e  X X\nX XX  XX X\nX        X\nXT   e   X\nXXXXXXXXXX\n", "Health: 8 X: 8 Y: 12\nXXXXXXXXXX\nXXXT     X\nXXXXXXXX X\nX     \u221e  X\nX XX XXXXX\nX XX XXXXX\nX MX XT tX\nX XX XTX X\nX XX XTX X\nX MXmXTX X\nX XXoXXX X\nX P    P X\nX XXXXXXHX\nXTX    X X\nX X \u221e  X X\nX XX  XX X\nX        X\nXT   e   X\nXXXXXXXXXX\n", "Health: 8 X: 8 Y: 11\nXXXXXXXXXX\nXXXT     X\nXXXXXXXX X\nX     \u221e  X\nX XX XXXXX\nX XX XXXXX\nX MX XT tX\nX XX XTX X\nX XX XTX X\nX MXmXTX X\nX XXoXXX X\nX P    PHX\nX XXXXXX X\nXTX    X X\nX X \u221e  X X\nX XX  XX X\nX        X\nXT   e   X\nXXXXXXXXXX\n", "Health: 10 X: 7 Y: 11\nXXXXXXXXXX\nXXXT     X\nXXXXXXXX X\nX     \u221e  X\nX XX XXXXX\nX XX XXXXX\nX MX XT tX\nX XX XTX X\nX XX XTX X\nX MX XTX X\nX XX\u221eXXX X\nX P      X\nX XXXXXX X\nXTX    X X\nX X \u221e  X X\nX XX  XX X\nX        X\nXT   e   X\nXXXXXXXXXX\n", "Health: 10 X: 8 Y: 11\nXXXXXXXXXX\nXXXT     X\nXXXXXXXX X\nX     \u221e  X\nX XX XXXXX\nX XX XXXXX\nX MX XT tX\nX XX XTX X\nX XX XTX X\nX MX XTX X\nX XX\u221eXXX X\nX P     HX\nX XXXXXX X\nXTX    X X\nX X \u221e  X X\nX XX  XX X\nX        X\nXT   e   X\nXXXXXXXXXX\n", "Health: 10 X: 8 Y: 12\nXXXXXXXXXX\nXXXT     X\nXXXXXXXX X\nX     \u221e  X\nX XX XXXXX\nX XX XXXXX\nX MX XT tX\nX XX XTX X\nX XX XTX X\nX MX XTX X\nX XX\u221eXXX X\nX P      X\nX XXXXXXHX\nXTX    X X\nX X \u221e  X X\nX XX  XX X\nX        X\nXT   e   X\nXXXXXXXXXX\n", "Health: 10 X: 8 Y: 13\nXXXXXXXXXX\nXXXT     X\nXXXXXXXX X\nX     \u221e  X\nX XX XXXXX\nX XX XXXXX\nX MX XT tX\nX XX XTX X\nX XX XTX X\nX MX XTX X\nX XX\u221eXXX X\nX P      X\nX XXXXXX X\nXTX    X X\nX X \u221e  X X\nX XX  XX X\nX        X\nXT   e   X\nXXXXXXXXXX\n", "Health: 10 X: 8 Y: 14\nXXXXXXXXXX\nXXXT     X\nXXXXXXXX X\nX     \u221e  X\nX XX XXXXX\nX XX XXXXX\nX MX XT tX\nX XX XTX X\nX XX XTX X\nX MX XTX X\nX XX\u221eXXX X\nX P      X\nX XXXXXX X\nXTX    X X\nX X \u221e  XHX\nX XX  XX X\nX        X\nXT   e   X\nXXXXXXXXXX\n", "Health: 10 X: 8 Y: 15\nXXXXXXXXXX\nXXXT     X\nXXXXXXXX X\nX     \u221e  X\nX XX XXXXX\nX XX XXXXX\nX MX XT tX\nX XX XTX X\nX XX XTX X\nX MX XTX X\nX XX\u221eXXX X\nX P      X\nX XXXXXX X\nXTX    X X\nX X \u221e  X X\nX XX  XXHX\nX        X\nXT   e   X\nXXXXXXXXXX\n", "Health: 10 X: 8 Y: 16\nXXXXXXXXXX\nXXXT     X\nXXXXXXXX X\nX     \u221e  X\nX XX XXXXX\nX XX XXXXX\nX MX XT tX\nX XX XTX X\nX XX XTX X\nX MX XTX X\nX XX\u221eXXX X\nX P m    X\nX XXXXXX X\nXTX    X X\nX X \u221e  X X\nX XX  XX X\nX       HX\nXT   e   X\nXXXXXXXXXX\n", "Health: 10 X: 7 Y: 16\nXXXXXXXXXX\nXXXT     X\nXXXXXXXX X\nX     \u221e  X\nX XX XXXXX\nX XX XXXXX\nX MX XT tX\nX XX XTX X\nX XX XTX X\nX MX XTX X\nX XX\u221eXXX X\nX P  m   X\nX XXXXXX X\nXTX    X X\nX X \u221e  X X\nX XX  XX X\nX      H X\nXT   e   X\nXXXXXXXXXX\n", "Health: 10 X: 6 Y: 16\nXXXXXXXXXX\nXXXT     X\nXXXXXXXX X\nX     \u221e  X\nX XX XXXXX\nX XX XXXXX\nX MX XT tX\nX XX XTX X\nX XX XTX X\nX MX XTX X\nX XX\u221eXXX X\nX P   m  X\nX XXXXXX X\nXTX    X X\nX X \u221e  X X\nX XX  XX X\nX     H  X\nXT   e   X\nXXXXXXXXXX\n", "Health: 10 X: 5 Y: 16\nXXXXXXXXXX\nXXXT     X\nXXXXXXXX X\nX     \u221e  X\nX XX XXXXX\nX XX XXXXX\nX MX XT tX\nX XX XTX X\nX XX XTX X\nX MX XTX X\nX XX\u221eXXX X\nX P      X\nX XXXXXX X\nXTX    X X\nX X \u221e  X X\nX XX  XX X\nX        X\nXT   e   X\nXXXXXXXXXX\n", "Health: 10 X: 4 Y: 16\nXXXXXXXXXX\nXXXT     X\nXXXXXXXX X\nX     \u221e  X\nX XX XXXXX\nX XX XXXXX\nX MX XT tX\nX XX XTX X\nX XX XTX X\nX MX XTX X\nX XX\u221eXXX X\nX P     mX\nX XXXXXX X\nXTX    X X\nX X \u221e  X X\nX XX  XX X\nX        X\nXT   e   X\nXXXXXXXXXX\n", "Health: 10 X: 3 Y: 16\nXXXXXXXXXX\nXXXT     X\nXXXXXXXX X\nX     \u221e  X\nX XX XXXXX\nX XX XXXXX\nX MX XT tX\nX XX XTX X\nX XX XTX X\nX MX XTX X\nX XX\u221eXXX X\nX P      X\nX XXXXXXmX\nXTX    X X\nX X \u221e  X X\nX XX  XX X\nX  H     X\nXT   e   X\nXXXXXXXXXX\n", "Health: 10 X: 2 Y: 16\nXXXXXXXXXX\nXXXT     X\nXXXXXXXX X\nX     \u221e  X\nX XX XXXXX\nX XX XXXXX\nX MX XT tX\nX XX XTX X\nX XX XTX X\nX MX XTX X\nX XX\u221eXXX X\nX P      X\nX XXXXXX X\nXTX    X X\nX X \u221e  X X\nX XX  XX X\nX H      X\nXT   e   X\nXXXXXXXXXX\n", "Health: 10 X: 1 Y: 16\nXXXXXXXXXX\nXXXT     X\nXXXXXXXX X\nX     \u221e  X\nX XX XXXXX\nX XX XXXXX\nX MX XT tX\nX XX XTX X\nX XX XTX X\nX MX XTX X\nX XX\u221eXXX X\nX P      X\nX XXXXXX X\nXTX    X X\nX X \u221e  XmX\nX XX  XX X\nXH       X\nXT   e   X\nXXXXXXXXXX\n", "Health: 10 X: 1 Y: 15\nXXXXXXXXXX\nXXXT     X\nXXXXXXXX X\nX     \u221e  X\nX XX XXXXX\nX XX XXXXX\nX MX XT tX\nX XX XTX X\nX XX XTX X\nX MX XTX X\nX XX\u221eXXX X\nX P      X\nX XXXXXX X\nXTX    X X\nX X \u221e  X X\nXHXX  XXmX\nX        X\nXT   e   X\nXXXXXXXXXX\n", "Health: 10 X: 1 Y: 14\nXXXXXXXXXX\nXXXT     X\nXXXXXXXX X\nX     \u221e  X\nX XX XXXXX\nX XX XXXXX\nX MX XT tX\nX XX XTX X\nX XX XTX X\nX MX XTX X\nX XX\u221eXXX X\nX P      X\nX XXXXXX X\nXTX    X X\nXHX \u221e  X X\nX XX  XX X\nX       mX\nXT   e   X\nXXXXXXXXXX\n", "Health: 10 X: 1 Y: 13\nXXXXXXXXXX\nXXXT     X\nXXXXXXXX X\nX     \u221e  X\nX XX XXXXX\nX XX XXXXX\nX MX XT tX\nX XX XTX X\nX XX XTX X\nX MX XTX X\nX XX\u221eXXX X\nX P      X\nX XXXXXX X\nX X    X X\nX X \u221e  X X\nX XX  XX X\nX      m X\nXT   e   X\nXXXXXXXXXX\n", "Health: 10 X: 1 Y: 12\nXXXXXXXXXX\nXXXT     X\nXXXXXXXX X\nX     \u221e  X\nX XX XXXXX\nX XX XXXXX\nX MX XT tX\nX XX XTX X\nX XX XTX X\nX MX XTX X\nX XX\u221eXXX X\nX P      X\nXHXXXXXX X\nX X    X X\nX X \u221e  X X\nX XX  XX X\nX     m  X\nXT   e   X\nXXXXXXXXXX\n", "Health: 10 X: 1 Y: 11\nXXXXXXXXXX\nXXXT     X\nXXXXXXXX X\nX     \u221e  X\nX XX XXXXX\nX XX XXXXX\nX MX XT tX\nX XX XTX X\nX XX XTX X\nX MX XTX X\nX XX\u221eXXX X\nXHP      X\nX XXXXXX X\nX X    X X\nX X \u221e  X X\nX XX  XX X\nX        X\nXT   e   X\nXXXXXXXXXX\n", "Health: 12 X: 2 Y: 11\nXXXXXXXXXX\nXXXT     X\nXXXXXXXX X\nX     \u221e  X\nX XX XXXXX\nX XX XXXXX\nX MX XT tX\nX XX XTX X\nX XX XTX X\nX MX XTX X\nX XX\u221eXXX X\nX        X\nX XXXXXX X\nX X    X X\nX X \u221e  X X\nX XX  XX X\nX        X\nXT   e   X\nXXXXXXXXXX\n", "Health: 12 X: 3 Y: 11\nXXXXXXXXXX\nXXXT     X\nXXXXXXXX X\nX     \u221e  X\nX XX XXXXX\nX XX XXXXX\nX MX XT tX\nX XX XTX X\nX XX XTX X\nX MX XTX X\nX XX\u221eXXX X\nX  H     X\nX XXXXXX X\nX X    X X\nX X \u221e  X X\nX XX  XX X\nX  m     X\nXT   e   X\nXXXXXXXXXX\n", "Health: 12 X: 4 Y: 11\nXXXXXXXXXX\nXXXT     X\nXXXXXXXX X\nX     \u221e  X\nX XX XXXXX\nX XX XXXXX\nX MX XT tX\nX XX XTX X\nX XX XTX X\nX MX XTX X\nX XX\u221eXXX X\nX   H    X\nX XXXXXX X\nX X    X X\nX X \u221e  X X\nX XX  XX X\nX m      X\nXT   e   X\nXXXXXXXXXX\n", "Health: 12 X: 5 Y: 11\nXXXXXXXXXX\nXXXT     X\nXXXXXXXX X\nX     \u221e  X\nX XX XXXXX\nX XX XXXXX\nX MX XT tX\nX XX XTX X\nX XX XTX X\nX MX XTX X\nX XX\u221eXXX X\nX    H   X\nX XXXXXX X\nX X    X X\nX X \u221e  X X\nX XX  XX X\nXm       X\nXT   e   X\nXXXXXXXXXX\n", "Health: 12 X: 6 Y: 11\nXXXXXXXXXX\nXXXT     X\nXXXXXXXX X\nX     \u221e  X\nX XX XXXXX\nX XX XXXXX\nX MX XT tX\nX XX XTX X\nX XX XTX X\nX MX XTX X\nX XX\u221eXXX X\nX     H  X\nX XXXXXX X\nX X    X X\nX X \u221e  X X\nXmXX  XX X\nX        X\nXT   e   X\nXXXXXXXXXX\n", "Health: 12 X: 7 Y: 11\nXXXXXXXXXX\nXXXT     X\nXXXXXXXX X\nX     \u221e  X\nX XX XXXXX\nX XX XXXXX\nX MX XT tX\nX XX XTX X\nX XX XTX X\nX MX XTX X\nX XX\u221eXXX X\nX        X\nX XXXXXX X\nX X    X X\nXmX \u221e  X X\nX XX  XX X\nX        X\nXT   e   X\nXXXXXXXXXX\n", "Health: 12 X: 8 Y: 11\nXXXXXXXXXX\nXXXT     X\nXXXXXXXX X\nX     \u221e  X\nX XX XXXXX\nX XX XXXXX\nX MX XT tX\nX XX XTX X\nX XX XTX X\nX MX XTX X\nX XX\u221eXXX X\nX       HX\nX XXXXXX X\nX X    X X\nX X \u221e  X X\nX XX  XX X\nX        X\nXT   e   X\nXXXXXXXXXX\n", "Health: 12 X: 8 Y: 10\nXXXXXXXXXX\nXXXT     X\nXXXXXXXX X\nX     \u221e  X\nX XX XXXXX\nX XX XXXXX\nX MX XT tX\nX XX XTX X\nX XX XTX X\nX MX XTX X\nX XX\u221eXXXHX\nX        X\nXmXXXXXX X\nX X    X X\nX X \u221e  X X\nX XX  XX X\nX        X\nXT   e   X\nXXXXXXXXXX\n", "Health: 12 X: 8 Y: 9\nXXXXXXXXXX\nXXXT     X\nXXXXXXXX X\nX     \u221e  X\nX XX XXXXX\nX XX XXXXX\nX MX XT tX\nX XX XTX X\nX XX XTX X\nX MX XTXHX\nX XX\u221eXXX X\nXm       X\nX XXXXXX X\nX X    X X\nX X \u221e  X X\nX XX  XX X\nX        X\nXT   e   X\nXXXXXXXXXX\n", "Health: 12 X: 8 Y: 8\nXXXXXXXXXX\nXXXT     X\nXXXXXXXX X\nX     \u221e  X\nX XX XXXXX\nX XX XXXXX\nX MX XT tX\nX XX XTX X\nX XX XTXHX\nX MX XTX X\nX XX\u221eXXX X\nX        X\nX XXXXXX X\nX X    X X\nX X \u221e  X X\nX XX  XX X\nX        X\nXT   e   X\nXXXXXXXXXX\n", "Health: 12 X: 8 Y: 7\nXXXXXXXXXX\nXXXT     X\nXXXXXXXX X\nX     \u221e  X\nX XX XXXXX\nX XX XXXXX\nX MX XT tX\nX XX XTXHX\nX XX XTX X\nX MX XTX X\nX XX\u221eXXX X\nX  m     X\nX XXXXXX X\nX X    X X\nX X \u221e  X X\nX XX  XX X\nX        X\nXT   e   X\nXXXXXXXXXX\n", "Health: 11 X: 8 Y: 6\nXXXXXXXXXX\nXXXT     X\nXXXXXXXX X\nX     \u221e  X\nX XX XXXXX\nX XX XXXXX\nX MX XT tX\nX XX XTX X\nX XX XTX X\nX MX XTX X\nX XX\u221eXXX X\nX   m    X\nX XXXXXX X\nX X    X X\nX X \u221e  X X\nX XX  XX X\nX        X\nXT   e   X\nXXXXXXXXXX\n", "Health: 11 X: 7 Y: 6\nXXXXXXXXXX\nXXXT     X\nXXXXXXXX X\nX     \u221e  X\nX XX XXXXX\nX XX XXXXX\nX MX XTHtX\nX XX XTX X\nX XX XTX X\nX MX XTX X\nX XX\u221eXXX X\nX    m   X\nX XXXXXX X\nX X    X X\nX X \u221e  X X\nX XX  XX X\nX        X\nXT   e   X\nXXXXXXXXXX\n", "Health: 11 X: 6 Y: 6\nXXXXXXXXXX\nXXXT     X\nXXXXXXXX X\nX     \u221e  X\nX XX XXXXX\nX XX XXXXX\nX MX X  tX\nX XX XTX X\nX XX XTX X\nX MX XTX X\nX XX\u221eXXX X\nX     m  X\nX XXXXXX X\nX X    X X\nX X \u221e  X X\nX XX  XX X\nX        X\nXT   e   X\nXXXXXXXXXX\n", "Health: 11 X: 6 Y: 7\nXXXXXXXXXX\nXXXT     X\nXXXXXXXX X\nX     \u221e  X\nX XX XXXXX\nX XX XXXXX\nX MX X  tX\nX XX X X X\nX XX XTX X\nX MX XTX X\nX XX\u221eXXX X\nX        X\nX XXXXXX X\nX X    X X\nX X \u221e  X X\nX XX  XX X\nX        X\nXT   e   X\nXXXXXXXXXX\n", "Health: 11 X: 6 Y: 8\nXXXXXXXXXX\nXXXT     X\nXXXXXXXX X\nX     \u221e  X\nX XX XXXXX\nX XX XXXXX\nX MX X  tX\nX XX X X X\nX XX X X X\nX MX XTX X\nX XX\u221eXXX X\nX       mX\nX XXXXXX X\nX X    X X\nX X \u221e  X X\nX XX  XX X\nX        X\nXT   e   X\nXXXXXXXXXX\n", "Health: 11 X: 6 Y: 9\nXXXXXXXXXX\nXXXT     X\nXXXXXXXX X\nX     \u221e  X\nX XX XXXXX\nX XX XXXXX\nX MX X  tX\nX XX X X X\nX XX X X X\nX MX X X X\nX XX\u221eXXXmX\nX        X\nX XXXXXX X\nX X    X X\nX X \u221e  X X\nX XX  XX X\nX        X\nXT   e   X\nXXXXXXXXXX\n", "Health: 11 X: 6 Y: 8\nXXXXXXXXXX\nXXXT     X\nXXXXXXXX X\nX     \u221e  X\nX XX XXXXX\nX XX XXXXX\nX MX X  tX\nX XX X X X\nX XX X X X\nX MX X XmX\nX XX\u221eXXX X\nX        X\nX XXXXXX X\nX X    X X\nX X \u221e  X X\nX XX  XX X\nX        X\nXT   e   X\nXXXXXXXXXX\n", "Health: 11 X: 6 Y: 7\nXXXXXXXXXX\nXXXT     X\nXXXXXXXX X\nX     \u221e  X\nX XX XXXXX\nX XX XXXXX\nX MX X  tX\nX XX X X X\nX XX X XmX\nX MX X X X\nX XX\u221eXXX X\nX        X\nX XXXXXX X\nX X    X X\nX X \u221e  X X\nX XX  XX X\nX        X\nXT   e   X\nXXXXXXXXXX\n", "Health: 11 X: 6 Y: 6\nXXXXXXXXXX\nXXXT     X\nXXXXXXXX X\nX     \u221e  X\nX XX XXXXX\nX XX XXXXX\nX MX X  tX\nX XX X XmX\nX XX X X X\nX MX X X X\nX XX\u221eXXX X\nX        X\nX XXXXXX X\nX X    X X\nX X \u221e  X X\nX XX  XX X\nX        X\nXT   e   X\nXXXXXXXXXX\n", "Health: 11 X: 6 Y: 7\nXXXXXXXXXX\nXXXT     X\nXXXXXXXX X\nX     \u221e  X\nX XX XXXXX\nX XX XXXXX\nX MX X  tX\nX XX X X X\nX XX X X X\nX MX X X X\nX XX\u221eXXX X\nX        X\nX XXXXXX X\nX X    X X\nX X \u221e  X X\nX XX  XX X\nX        X\nXT   e   X\nXXXXXXXXXX\n", "Health: 11 X: 6 Y: 6\nXXXXXXXXXX\nXXXT     X\nXXXXXXXX X\nX     \u221e  X\nX XX XXXXX\nX XX XXXXX\nX MX X  tX\nX XX X X X\nX XX X X X\nX MX X X X\nX XX\u221eXXX X\nX        X\nX XXXXXX X\nX X    X X\nX X \u221e  X X\nX XX  XX X\nX        X\nXT   e   X\nXXXXXXXXXX\n", "Health: 11 X: 7 Y: 6\nXXXXXXXXXX\nXXXT     X\nXXXXXXXX X\nX     \u221e  X\nX XX XXXXX\nX XX XXXXX\nX MX X HtX\nX XX X X X\nX XX X X X\nX MX X X X\nX XX\u221eXXX X\nX        X\nX XXXXXX X\nX X    X X\nX X \u221e  X X\nX XX  XX X\nX        X\nXT   e   X\nXXXXXXXXXX\n", "Health: 10 X: 8 Y: 6\nXXXXXXXXXX\nXXXT     X\nXXXXXXXX X\nX     \u221e  X\nX XX XXXXX\nX XX XXXXX\nX MX X  tX\nX XX X X X\nX XX X X X\nX MX X X X\nX XX\u221eXXX X\nX        X\nX XXXXXX X\nX X    X X\nX X \u221e  X X\nX XX  XX X\nX        X\nXT   e   X\nXXXXXXXXXX\n", "Health: 10 X: 8 Y: 7\nXXXXXXXXXX\nXXXT     X\nXXXXXXXX X\nX     \u221e  X\nX XX XXXXX\nX XX XXXXX\nX MX X  tX\nX XX X XHX\nX XX X X X\nX MX X X X\nX XX\u221eXXX X\nX        X\nX XXXXXX X\nX X    X X\nX X \u221e  X X\nX XX  XX X\nX        X\nXT   e   X\nXXXXXXXXXX\n", "Health: 10 X: 8 Y: 8\nXXXXXXXXXX\nXXXT     X\nXXXXXXXX X\nX     \u221e  X\nX XX XXXXX\nX XX XXXXX\nX MX X  tX\nX XX X X X\nX XX X XHX\nX MX X X X\nX XX\u221eXXX X\nX        X\nX XXXXXX X\nX X    X X\nX X \u221e  X X\nX XX  XX X\nX        X\nXT   e   X\nXXXXXXXXXX\n", "Health: 10 X: 8 Y: 9\nXXXXXXXXXX\nXXXT     X\nXXXXXXXX X\nX     \u221e  X\nX XX XXXXX\nX XX XXXXX\nX MX X  tX\nX XX X XmX\nX XX X X X\nX MX X XHX\nX XX\u221eXXX X\nX        X\nX XXXXXX X\nX X    X X\nX X \u221e  X X\nX XX  XX X\nX        X\nXT   e   X\nXXXXXXXXXX\n", "Health: 10 X: 8 Y: 10\nXXXXXXXXXX\nXXXT     X\nXXXXXXXX X\nX     \u221e  X\nX XX XXXXX\nX XX XXXXX\nX MX X  tX\nX XX X X X\nX XX X XmX\nX MX X X X\nX XX\u221eXXXHX\nX        X\nX XXXXXX X\nX X    X X\nX X \u221e  X X\nX XX  XX X\nX        X\nXT   e   X\nXXXXXXXXXX\n", "Health: 10 X: 8 Y: 11\nXXXXXXXXXX\nXXXT     X\nXXXXXXXX X\nX     \u221e  X\nX XX XXXXX\nX XX XXXXX\nX MX X  tX\nX XX X X X\nX XX X X X\nX MX X XmX\nX XX\u221eXXX X\nX       HX\nX XXXXXX X\nX X    X X\nX X \u221e  X X\nX XX  XX X\nX        X\nXT   e   X\nXXXXXXXXXX\n", "Health: 10 X: 8 Y: 12\nXXXXXXXXXX\nXXXT     X\nXXXXXXXX X\nX     \u221e  X\nX XX XXXXX\nX XX XXXXX\nX MX X  tX\nX XX X X X\nX XX X X X\nX MX X X X\nX XX\u221eXXXmX\nX        X\nX XXXXXXHX\nX X    X X\nX X \u221e  X X\nX XX  XX X\nX        X\nXT   e   X\nXXXXXXXXXX\n", "Health: 10 X: 8 Y: 13\nXXXXXXXXXX\nXXXT     X\nXXXXXXXX X\nX     \u221e  X\nX XX XXXXX\nX XX XXXXX\nX MX X  tX\nX XX X X X\nX XX X X X\nX MX X X X\nX XX\u221eXXX X\nX       mX\nX XXXXXX X\nX X    X X\nX X \u221e  X X\nX XX  XX X\nX        X\nXT   e   X\nXXXXXXXXXX\n", "Health: 10 X: 8 Y: 14\nXXXXXXXXXX\nXXXT     X\nXXXXXXXX X\nX     \u221e  X\nX XX XXXXX\nX XX XXXXX\nX MX X  tX\nX XX X X X\nX XX X X X\nX MX X X X\nX XX\u221eXXX X\nX        X\nX XXXXXXmX\nX X    X X\nX X \u221e  XHX\nX XX  XX X\nX        X\nXT   e   X\nXXXXXXXXXX\n", "Health: 10 X: 8 Y: 15\nXXXXXXXXXX\nXXXT     X\nXXXXXXXX X\nX     \u221e  X\nX XX XXXXX\nX XX XXXXX\nX MX X  tX\nX XX X X X\nX XX X X X\nX MX X X X\nX XX\u221eXXX X\nX        X\nX XXXXXX X\nX X    X X\nX X \u221e  X X\nX XX  XXHX\nX        X\nXT   e   X\nXXXXXXXXXX\n", "Health: 10 X: 8 Y: 16\nXXXXXXXXXX\nXXXT     X\nXXXXXXXX X\nX     \u221e  X\nX XX XXXXX\nX XX XXXXX\nX MX X  tX\nX XX X X X\nX XX X X X\nX MX X X X\nX XX\u221eXXX X\nX        X\nX XXXXXX X\nX X    X X\nX X \u221e  XmX\nX XX  XX X\nX       HX\nXT   e   X\nXXXXXXXXXX\n", "Health: 10 X: 8 Y: 17\nXXXXXXXXXX\nXXXT     X\nXXXXXXXX X\nX     \u221e  X\nX XX XXXXX\nX XX XXXXX\nX MX X  tX\nX XX X X X\nX XX X X X\nX MX X X X\nX XX\u221eXXX X\nX        X\nX XXXXXX X\nX X    X X\nX X \u221e  X X\nX XX  XXmX\nX        X\nXT   e  HX\nXXXXXXXXXX\n", "Health: 10 X: 7 Y: 17\nXXXXXXXXXX\nXXXT     X\nXXXXXXXX X\nX     \u221e  X\nX XX XXXXX\nX XX XXXXX\nX MX X  tX\nX XX X X X\nX XX X X X\nX MX X X X\nX XX\u221eXXX X\nX        X\nX XXXXXX X\nX X    X X\nX X \u221e  X X\nX XX  XX X\nX       mX\nXT   e H X\nXXXXXXXXXX\n", "Health: 10 X: 6 Y: 17\nXXXXXXXXXX\nXXXT     X\nXXXXXXXX X\nX     \u221e  X\nX XX XXXXX\nX XX XXXXX\nX MX X  tX\nX XX X X X\nX XX X X X\nX MX X X X\nX XX\u221eXXX X\nX        X\nX XXXXXX X\nX X    X X\nX X \u221e  X X\nX XX  XX X\nX      m X\nXT   eH  X\nXXXXXXXXXX\n", "Health: 10 X: 5 Y: 17\nXXXXXXXXXX\nXXXT     X\nXXXXXXXX X\nX     \u221e  X\nX XX XXXXX\nX XX XXXXX\nX MX X  tX\nX XX X X X\nX XX X X X\nX MX X X X\nX XX\u221eXXX X\nX        X\nX XXXXXX X\nX X    X X\nX X \u221e  X X\nX XX  XX X\nX     m  X\nXT   e   X\nXXXXXXXXXX\n"], "map_number": 201}, {"mechanics": [{"timestep": 20, "mechanic": "CollectTreasure"}, {"timestep": 28, "mechanic": "BlobHit"}, {"timestep": 35, "mechanic": "CollectTreasure"}, {"timestep": 36, "mechanic": "CollectTreasure"}, {"timestep": 46, "mechanic": "CollectTreasure"}, {"timestep": 47, "mechanic": "CollectTreasure"}, {"timestep": 48, "mechanic": "CollectTreasure"}, {"timestep": 49, "mechanic": "CollectTreasure"}, {"timestep": 51, "mechanic": "JavelinThrow"}, {"timestep": 53, "mechanic": "MinitaurHit"}, {"timestep": 56, "mechanic": "MinitaurHit"}, {"timestep": 77, "mechanic": "CollectPotion"}, {"timestep": 82, "mechanic": "JavelinThrow"}, {"timestep": 84, "mechanic": "MinitaurHit"}, {"timestep": 88, "mechanic": "ReachStairs"}], "frequencies": {"CollectTreasure": 7, "BlobHit": 1, "JavelinThrow": 2, "MinitaurHit": 3, "CollectPotion": 1, "ReachStairs": 1}, "levelReport": {"utilityGained": 0.0, "exitUtility": 1.0, "runnerUtility": 0.10999999999999999, "loitererUtility": 89.0, "completionistUtility": 0.8166666666666667, "monsterKillerUtility": 0.8, "treasureCollectorUtility": 1.0, "turnsTaken": 89, "health": 10, "healthLost": 2, "alive": true, "javelinsThrown": 2, "monsterKills": 5, "minitaurKnockouts": 6, "treasuresCollected": 7, "potionsTaken": 1, "totalMonsters": 8, "totalTreasures": 7, "totalPotions": 2, "timeTaken": 0.0}, "positions": [{"X": 4, "Y": 10}, {"X": 5, "Y": 10}, {"X": 6, "Y": 10}, {"X": 5, "Y": 10}, {"X": 5, "Y": 11}, {"X": 5, "Y": 12}, {"X": 4, "Y": 12}, {"X": 3, "Y": 12}, {"X": 2, "Y": 12}, {"X": 1, "Y": 12}, {"X": 1, "Y": 13}, {"X": 1, "Y": 14}, {"X": 2, "Y": 14}, {"X": 3, "Y": 14}, {"X": 4, "Y": 14}, {"X": 5, "Y": 14}, {"X": 6, "Y": 14}, {"X": 7, "Y": 14}, {"X": 7, "Y": 13}, {"X": 7, "Y": 12}, {"X": 8, "Y": 12}, {"X": 7, "Y": 12}, {"X": 7, "Y": 13}, {"X": 7, "Y": 14}, {"X": 6, "Y": 14}, {"X": 5, "Y": 14}, {"X": 6, "Y": 14}, {"X": 6, "Y": 15}, {"X": 6, "Y": 16}, {"X": 5, "Y": 16}, {"X": 5, "Y": 17}, {"X": 5, "Y": 18}, {"X": 6, "Y": 18}, {"X": 7, "Y": 18}, {"X": 8, "Y": 18}, {"X": 8, "Y": 17}, {"X": 8, "Y": 16}, {"X": 8, "Y": 17}, {"X": 8, "Y": 18}, {"X": 7, "Y": 18}, {"X": 6, "Y": 18}, {"X": 5, "Y": 18}, {"X": 4, "Y": 18}, {"X": 3, "Y": 18}, {"X": 2, "Y": 18}, {"X": 1, "Y": 18}, {"X": 1, "Y": 17}, {"X": 1, "Y": 16}, {"X": 2, "Y": 16}, {"X": 2, "Y": 17}, {"X": 2, "Y": 18}, {"X": 2, "Y": 18}, {"X": 3, "Y": 18}, {"X": 4, "Y": 18}, {"X": 5, "Y": 18}, {"X": 6, "Y": 18}, {"X": 5, "Y": 18}, {"X": 5, "Y": 17}, {"X": 5, "Y": 16}, {"X": 6, "Y": 16}, {"X": 6, "Y": 15}, {"X": 6, "Y": 14}, {"X": 5, "Y": 14}, {"X": 4, "Y": 14}, {"X": 3, "Y": 14}, {"X": 2, "Y": 14}, {"X": 1, "Y": 14}, {"X": 1, "Y": 13}, {"X": 1, "Y": 12}, {"X": 2, "Y": 12}, {"X": 3, "Y": 12}, {"X": 4, "Y": 12}, {"X": 5, "Y": 12}, {"X": 5, "Y": 11}, {"X": 5, "Y": 10}, {"X": 6, "Y": 10}, {"X": 7, "Y": 10}, {"X": 8, "Y": 10}, {"X": 7, "Y": 10}, {"X": 7, "Y": 9}, {"X": 6, "Y": 9}, {"X": 7, "Y": 9}, {"X": 7, "Y": 9}, {"X": 6, "Y": 9}, {"X": 5, "Y": 9}, {"X": 4, "Y": 9}, {"X": 3, "Y": 9}, {"X": 2, "Y": 9}, {"X": 1, "Y": 9}], "levelStates": ["Health: 10 X: 4 Y: 10\nXXXXXXXXXX\nX   m    X\nX XXXXXX X\nXR      RX\nXXXX  XXXX\nX     M  X\nX  M     X\nX      M X\nXXX    XXX\nXe      PX\nX   H   PX\nXXXXX XXXX\nX     X TX\nX XXXXX XX\nX        X\nXXXXXX XXX\nXTTX   XTX\nXTTXX XXTX\nX    b   X\nXXXXXXXXXX\n", "Health: 10 X: 5 Y: 10\nXXXXXXXXXX\nX   m    X\nX XXXXXX X\nXR      RX\nXXXX  XXXX\nX    M   X\nX   M    X\nX      M X\nXXX    XXX\nXe      PX\nX    H  PX\nXXXXX XXXX\nX     X TX\nX XXXXX XX\nX        X\nXXXXXX XXX\nXTTX   XTX\nXTTXX XXTX\nX    b   X\nXXXXXXXXXX\n", "Health: 10 X: 6 Y: 10\nXXXXXXXXXX\nX   m    X\nX XXXXXX X\nXR      RX\nXXXX  XXXX\nX     M  X\nX        X\nX   M  M X\nXXX    XXX\nXe      PX\nX     H PX\nXXXXX XXXX\nX     X TX\nX XXXXX XX\nX        X\nXXXXXX XXX\nXTTX   XTX\nXTTXX XXTX\nX    b   X\nXXXXXXXXXX\n", "Health: 10 X: 5 Y: 10\nXXXXXXXXXX\nX   m    X\nX XXXXXX X\nXR      RX\nXXXX  XXXX\nX    M   X\nX        X\nX    M M X\nXXX    XXX\nXe      PX\nX    H  PX\nXXXXX XXXX\nX     X TX\nX XXXXX XX\nX        X\nXXXXXX XXX\nXTTX   XTX\nXTTXX XXTX\nX    b   X\nXXXXXXXXXX\n", "Health: 10 X: 5 Y: 11\nXXXXXXXXXX\nX   m    X\nX XXXXXX X\nXR      RX\nXXXX  XXXX\nX        X\nX    M   X\nX      M X\nXXX  M XXX\nXe      PX\nX       PX\nXXXXXHXXXX\nX     X TX\nX XXXXX XX\nX        X\nXXXXXX XXX\nXTTX   XTX\nXTTXX XXTX\nX    b   X\nXXXXXXXXXX\n", "Health: 10 X: 5 Y: 12\nXXXXXXXXXX\nX   m    X\nX XXXXXX X\nXR      RX\nXXXX  XXXX\nX        X\nX        X\nX    M M X\nXXX    XXX\nXe   M  PX\nX       PX\nXXXXX XXXX\nX    HX TX\nX XXXXX XX\nX        X\nXXXXXX XXX\nXTTX   XTX\nXTTXX XXTX\nX    b   X\nXXXXXXXXXX\n", "Health: 10 X: 4 Y: 12\nXXXXXXXXXX\nX  m\u221e    X\nX XXXXXX X\nXR      RX\nXXXX  XXXX\nX        X\nX        X\nX    M M X\nXXX    XXX\nXe   M  PX\nX       PX\nXXXXX XXXX\nX   H X TX\nX XXXXX XX\nX        X\nXXXXXX XXX\nXTTX   XTX\nXTTXX XXTX\nX    b   X\nXXXXXXXXXX\n", "Health: 10 X: 3 Y: 12\nXXXXXXXXXX\nX m \u221e    X\nX XXXXXX X\nXR      RX\nXXXX  XXXX\nX        X\nX        X\nX    M M X\nXXX    XXX\nXe   M  PX\nX       PX\nXXXXX XXXX\nX  H  X TX\nX XXXXX XX\nX        X\nXXXXXX XXX\nXTTX   XTX\nXTTXX XXTX\nX    b   X\nXXXXXXXXXX\n", "Health: 10 X: 2 Y: 12\nXXXXXXXXXX\nXm  \u221e    X\nX XXXXXX X\nXR      RX\nXXXX  XXXX\nX        X\nX        X\nX    M M X\nXXX    XXX\nXe   M  PX\nX       PX\nXXXXX XXXX\nX H   X TX\nX XXXXX XX\nX        X\nXXXXXX XXX\nXTTX   XTX\nXTTXX XXTX\nX    b   X\nXXXXXXXXXX\n", "Health: 10 X: 1 Y: 12\nXXXXXXXXXX\nX   \u221e    X\nXmXXXXXX X\nXR      RX\nXXXX  XXXX\nX        X\nX        X\nX    M M X\nXXX    XXX\nXe   M  PX\nX       PX\nXXXXX XXXX\nXH    X TX\nX XXXXX XX\nX        X\nXXXXXX XXX\nXTTX   XTX\nXTTXX XXTX\nX    b   X\nXXXXXXXXXX\n", "Health: 10 X: 1 Y: 13\nXXXXXXXXXX\nX   \u221e    X\nX XXXXXX X\nX\u221e      RX\nXXXX  XXXX\nX        X\nX        X\nX    M M X\nXXX    XXX\nXe   M  PX\nX       PX\nXXXXX XXXX\nX     X TX\nXHXXXXX XX\nX        X\nXXXXXX XXX\nXTTX   XTX\nXTTXX XXTX\nX    b   X\nXXXXXXXXXX\n", "Health: 10 X: 1 Y: 14\nXXXXXXXXXX\nX   \u221e    X\nX XXXXXX X\nX\u221em     RX\nXXXX  XXXX\nX        X\nX        X\nX    M M X\nXXX    XXX\nXe   M  PX\nX       PX\nXXXXX XXXX\nX     X TX\nX XXXXX XX\nXH       X\nXXXXXX XXX\nXTTX   XTX\nXTTXX XXTX\nX    b   X\nXXXXXXXXXX\n", "Health: 10 X: 2 Y: 14\nXXXXXXXXXX\nX   \u221e    X\nX XXXXXX X\nX\u221e m    RX\nXXXX  XXXX\nX        X\nX        X\nX    M M X\nXXX    XXX\nXe   M  PX\nX       PX\nXXXXX XXXX\nX     X TX\nX XXXXX XX\nX H      X\nXXXXXX XXX\nXTTX   XTX\nXTTXX XXTX\nX    b   X\nXXXXXXXXXX\n", "Health: 10 X: 3 Y: 14\nXXXXXXXXXX\nX   \u221e    X\nX XXXXXX X\nX\u221e  m   RX\nXXXX  XXXX\nX        X\nX        X\nX    M M X\nXXX    XXX\nXe   M  PX\nX       PX\nXXXXX XXXX\nX     X TX\nX XXXXX XX\nX  H     X\nXXXXXX XXX\nXTTX   XTX\nXTTXX XXTX\nX    b   X\nXXXXXXXXXX\n", "Health: 10 X: 4 Y: 14\nXXXXXXXXXX\nX   \u221e    X\nX XXXXXX X\nX\u221e      RX\nXXXXm XXXX\nX        X\nX        X\nX    M M X\nXXX    XXX\nXe   M  PX\nX       PX\nXXXXX XXXX\nX     X TX\nX XXXXX XX\nX   H    X\nXXXXXX XXX\nXTTX   XTX\nXTTXX XXTX\nX    b   X\nXXXXXXXXXX\n", "Health: 10 X: 5 Y: 14\nXXXXXXXXXX\nX   \u221e    X\nX XXXXXX X\nX\u221e      RX\nXXXX mXXXX\nX        X\nX        X\nX    M M X\nXXX    XXX\nXe   M  PX\nX       PX\nXXXXX XXXX\nX     X TX\nX XXXXX XX\nX    H   X\nXXXXXX XXX\nXTTX   XTX\nXTTXX XXTX\nX    b   X\nXXXXXXXXXX\n", "Health: 10 X: 6 Y: 14\nXXXXXXXXXX\nX   \u221e    X\nX XXXXXX X\nX\u221e      RX\nXXXX  XXXX\nX    m   X\nX        X\nX    M M X\nXXX    XXX\nXe   M  PX\nX       PX\nXXXXX XXXX\nX     X TX\nX XXXXX XX\nX     H  X\nXXXXXX XXX\nXTTX   XTX\nXTTXXbXXTX\nX        X\nXXXXXXXXXX\n", "Health: 10 X: 7 Y: 14\nXXXXXXXXXX\nX   \u221e    X\nX XXXXXX X\nX\u221e      RX\nXXXX  XXXX\nX        X\nX    m   X\nX    M M X\nXXX    XXX\nXe   M  PX\nX       PX\nXXXXX XXXX\nX     X TX\nX XXXXX XX\nX      H X\nXXXXXX XXX\nXTTX   XTX\nXTTXXbXXTX\nX        X\nXXXXXXXXXX\n", "Health: 10 X: 7 Y: 13\nXXXXXXXXXX\nX   \u221e    X\nX XXXXXX X\nX\u221e      RX\nXXXX  XXXX\nX        X\nX        X\nX    \u221e M X\nXXX    XXX\nXe   M  PX\nX       PX\nXXXXX XXXX\nX     X TX\nX XXXXXHXX\nX        X\nXXXXXX XXX\nXTTX b XTX\nXTTXX XXTX\nX        X\nXXXXXXXXXX\n", "Health: 10 X: 7 Y: 12\nXXXXXXXXXX\nX   \u221e    X\nX XXXXXX X\nX\u221e      RX\nXXXX  XXXX\nX        X\nX        X\nX    \u221e M X\nXXX    XXX\nXe   M  PX\nX       PX\nXXXXX XXXX\nX     XHTX\nX XXXXX XX\nX        X\nXXXXXX XXX\nXTTX b XTX\nXTTXX XXTX\nX        X\nXXXXXXXXXX\n", "Health: 10 X: 8 Y: 12\nXXXXXXXXXX\nX   \u221e    X\nX XXXXXX X\nX\u221e      RX\nXXXX  XXXX\nX        X\nX        X\nX    \u221e M X\nXXX    XXX\nXe   M  PX\nX       PX\nXXXXX XXXX\nX     X  X\nX XXXXX XX\nX        X\nXXXXXX XXX\nXTTX b XTX\nXTTXX XXTX\nX        X\nXXXXXXXXXX\n", "Health: 10 X: 7 Y: 12\nXXXXXXXXXX\nX   \u221e    X\nX XXXXXX X\nX\u221e      RX\nXXXX  XXXX\nX        X\nX        X\nX    \u221e M X\nXXX    XXX\nXe   M  PX\nX       PX\nXXXXX XXXX\nX     XH X\nX XXXXX XX\nX        X\nXXXXXX XXX\nXTTX b XTX\nXTTXX XXTX\nX        X\nXXXXXXXXXX\n", "Health: 10 X: 7 Y: 13\nXXXXXXXXXX\nX   \u221e    X\nX XXXXXX X\nX\u221e      RX\nXXXX  XXXX\nX        X\nX        X\nX    \u221e M X\nXXX    XXX\nXe   M  PX\nX       PX\nXXXXX XXXX\nX     X  X\nX XXXXXHXX\nX        X\nXXXXXX XXX\nXTTX b XTX\nXTTXX XXTX\nX        X\nXXXXXXXXXX\n", "Health: 10 X: 7 Y: 14\nXXXXXXXXXX\nX   \u221e    X\nX XXXXXX X\nX\u221e      RX\nXXXX  XXXX\nX        X\nX        X\nX    \u221e M X\nXXX    XXX\nXe   M  PX\nX       PX\nXXXXX XXXX\nX     X  X\nX XXXXX XX\nX      H X\nXXXXXX XXX\nXTTX b XTX\nXTTXX XXTX\nX        X\nXXXXXXXXXX\n", "Health: 10 X: 6 Y: 14\nXXXXXXXXXX\nX   \u221e    X\nX XXXXXX X\nX\u221e      RX\nXXXX  XXXX\nX        X\nX        X\nX    \u221e M X\nXXX  m XXX\nXe   M  PX\nX       PX\nXXXXX XXXX\nX     X  X\nX XXXXX XX\nX     H  X\nXXXXXX XXX\nXTTX b XTX\nXTTXX XXTX\nX        X\nXXXXXXXXXX\n", "Health: 10 X: 5 Y: 14\nXXXXXXXXXX\nX   \u221e    X\nX XXXXXX X\nX\u221e      RX\nXXXX  XXXX\nX        X\nX        X\nX    \u221e M X\nXXX    XXX\nXe   \u221e  PX\nX       PX\nXXXXX XXXX\nX     X  X\nX XXXXX XX\nX    H   X\nXXXXXX XXX\nXTTX b XTX\nXTTXX XXTX\nX        X\nXXXXXXXXXX\n", "Health: 10 X: 6 Y: 14\nXXXXXXXXXX\nX   \u221e    X\nX XXXXXX X\nX\u221e      RX\nXXXX  XXXX\nX        X\nX        X\nX    \u221e M X\nXXX    XXX\nXe   \u221e  PX\nX       PX\nXXXXX XXXX\nX     X  X\nX XXXXX XX\nX     H  X\nXXXXXX XXX\nXTTX b XTX\nXTTXX XXTX\nX        X\nXXXXXXXXXX\n", "Health: 10 X: 6 Y: 15\nXXXXXXXXXX\nX   \u221e    X\nX XXXXXX X\nX\u221e      RX\nXXXX  XXXX\nX        X\nX        X\nX    \u221e M X\nXXX    XXX\nXe   \u221e  PX\nX       PX\nXXXXX XXXX\nX     X  X\nX XXXXX XX\nX        X\nXXXXXXHXXX\nXTTX b XTX\nXTTXX XXTX\nX        X\nXXXXXXXXXX\n", "Health: 9 X: 6 Y: 16\nXXXXXXXXXX\nX   \u221e    X\nX XXXXXX X\nX\u221e      RX\nXXXX  XXXX\nX        X\nX        X\nX    \u221e M X\nXXX    XXX\nXe   \u221e  PX\nX       PX\nXXXXX XXXX\nX     X  X\nX XXXXX XX\nX        X\nXXXXXX XXX\nXTTX \u221eHXTX\nXTTXX XXTX\nX        X\nXXXXXXXXXX\n", "Health: 9 X: 5 Y: 16\nXXXXXXXXXX\nX   \u221e    X\nX XXXXXX X\nX\u221e      RX\nXXXX  XXXX\nX        X\nX        X\nX    \u221e M X\nXXX    XXX\nXe   \u221e  PX\nX       PX\nXXXXX XXXX\nX     X  X\nX XXXXX XX\nX        X\nXXXXXX XXX\nXTTX \u221e XTX\nXTTXX XXTX\nX        X\nXXXXXXXXXX\n", "Health: 9 X: 5 Y: 17\nXXXXXXXXXX\nX   \u221e    X\nX XXXXXX X\nX\u221e      RX\nXXXX  XXXX\nX        X\nX        X\nX    \u221e M X\nXXX    XXX\nXe   \u221e  PX\nX       PX\nXXXXX XXXX\nX     X  X\nX XXXXX XX\nX        X\nXXXXXX XXX\nXTTX \u221e XTX\nXTTXXHXXTX\nX        X\nXXXXXXXXXX\n", "Health: 9 X: 5 Y: 18\nXXXXXXXXXX\nX   \u221e    X\nX XXXXXX X\nX\u221e      RX\nXXXX  XXXX\nX        X\nX        X\nX    \u221e M X\nXXX    XXX\nXe   \u221e  PX\nX    m  PX\nXXXXX XXXX\nX     X  X\nX XXXXX XX\nX        X\nXXXXXX XXX\nXTTX \u221e XTX\nXTTXX XXTX\nX    H   X\nXXXXXXXXXX\n", "Health: 9 X: 6 Y: 18\nXXXXXXXXXX\nX   \u221e    X\nX XXXXXX X\nX\u221e      RX\nXXXX  XXXX\nX        X\nX        X\nX    \u221e M X\nXXX    XXX\nXe   \u221e  PX\nX       PX\nXXXXXmXXXX\nX     X  X\nX XXXXX XX\nX        X\nXXXXXX XXX\nXTTX \u221e XTX\nXTTXX XXTX\nX     H  X\nXXXXXXXXXX\n", "Health: 9 X: 7 Y: 18\nXXXXXXXXXX\nX   \u221e    X\nX XXXXXX X\nX\u221e      RX\nXXXX  XXXX\nX        X\nX        X\nX    \u221e M X\nXXX    XXX\nXe   \u221e  PX\nX       PX\nXXXXX XXXX\nX    mX  X\nX XXXXX XX\nX        X\nXXXXXX XXX\nXTTX \u221e XTX\nXTTXX XXTX\nX      H X\nXXXXXXXXXX\n", "Health: 9 X: 8 Y: 18\nXXXXXXXXXX\nX   \u221e    X\nX XXXXXX X\nX\u221e      RX\nXXXX  XXXX\nX        X\nX        X\nX    \u221e M X\nXXX    XXX\nXe   \u221e  PX\nX       PX\nXXXXX XXXX\nX   m X  X\nX XXXXX XX\nX        X\nXXXXXX XXX\nXTTX \u221e XTX\nXTTXX XXTX\nX       HX\nXXXXXXXXXX\n", "Health: 9 X: 8 Y: 17\nXXXXXXXXXX\nX   \u221e    X\nX XXXXXX X\nX\u221e      RX\nXXXX  XXXX\nX        X\nX        X\nX    \u221e M X\nXXX    XXX\nXe   \u221e  PX\nX       PX\nXXXXX XXXX\nX  m  X  X\nX XXXXX XX\nX        X\nXXXXXX XXX\nXTTX \u221e XTX\nXTTXX XX X\nX        X\nXXXXXXXXXX\n", "Health: 9 X: 8 Y: 16\nXXXXXXXXXX\nX   \u221e    X\nX XXXXXX X\nX\u221e      RX\nXXXX  XXXX\nX        X\nX        X\nX    \u221e M X\nXXX    XXX\nXe   \u221e  PX\nX       PX\nXXXXX XXXX\nX m   X  X\nX XXXXX XX\nX        X\nXXXXXX XXX\nXTTX \u221e X X\nXTTXX XX X\nX        X\nXXXXXXXXXX\n", "Health: 9 X: 8 Y: 17\nXXXXXXXXXX\nX   \u221e    X\nX XXXXXX X\nX\u221e      RX\nXXXX  XXXX\nX        X\nX        X\nX    \u221e M X\nXXX    XXX\nXe   \u221e  PX\nX       PX\nXXXXX XXXX\nXm    X  X\nX XXXXX XX\nX        X\nXXXXXX XXX\nXTTX \u221e X X\nXTTXX XX X\nX        X\nXXXXXXXXXX\n", "Health: 9 X: 8 Y: 18\nXXXXXXXXXX\nX   \u221e    X\nX XXXXXX X\nX\u221e      RX\nXXXX  XXXX\nX        X\nX        X\nX    \u221e M X\nXXX    XXX\nXe   \u221e  PX\nX       PX\nXXXXX XXXX\nX     X  X\nXmXXXXX XX\nX        X\nXXXXXX XXX\nXTTX \u221e X X\nXTTXX XX X\nX       HX\nXXXXXXXXXX\n", "Health: 9 X: 7 Y: 18\nXXXXXXXXXX\nX   \u221e    X\nX XXXXXX X\nX\u221e      RX\nXXXX  XXXX\nX        X\nX        X\nX    \u221e M X\nXXX    XXX\nXe   \u221e  PX\nX       PX\nXXXXX XXXX\nX     X  X\nX XXXXX XX\nXm       X\nXXXXXX XXX\nXTTX \u221e X X\nXTTXX XX X\nX      H X\nXXXXXXXXXX\n", "Health: 9 X: 6 Y: 18\nXXXXXXXXXX\nX   \u221e    X\nX XXXXXX X\nX\u221e      RX\nXXXX  XXXX\nX        X\nX        X\nX    \u221e M X\nXXX    XXX\nXe   \u221e  PX\nX       PX\nXXXXX XXXX\nX     X  X\nX XXXXX XX\nX m      X\nXXXXXX XXX\nXTTX \u221e X X\nXTTXX XX X\nX     H  X\nXXXXXXXXXX\n", "Health: 9 X: 5 Y: 18\nXXXXXXXXXX\nX   \u221e    X\nX XXXXXX X\nX\u221e      RX\nXXXX  XXXX\nX        X\nX        X\nX    \u221e M X\nXXX    XXX\nXe   \u221e  PX\nX       PX\nXXXXX XXXX\nX     X  X\nX XXXXX XX\nX  m     X\nXXXXXX XXX\nXTTX \u221e X X\nXTTXX XX X\nX    H   X\nXXXXXXXXXX\n", "Health: 9 X: 4 Y: 18\nXXXXXXXXXX\nX   \u221e    X\nX XXXXXX X\nX\u221e      RX\nXXXX  XXXX\nX        X\nX        X\nX    \u221e M X\nXXX    XXX\nXe   \u221e  PX\nX       PX\nXXXXX XXXX\nX     X  X\nX XXXXX XX\nX   m    X\nXXXXXX XXX\nXTTX \u221e X X\nXTTXX XX X\nX   H    X\nXXXXXXXXXX\n", "Health: 9 X: 3 Y: 18\nXXXXXXXXXX\nX   \u221e    X\nX XXXXXX X\nX\u221e      RX\nXXXX  XXXX\nX        X\nX        X\nX    \u221e M X\nXXX    XXX\nXe   \u221e  PX\nX       PX\nXXXXX XXXX\nX     X  X\nX XXXXX XX\nX    m   X\nXXXXXX XXX\nXTTX \u221e X X\nXTTXX XX X\nX  H     X\nXXXXXXXXXX\n", "Health: 9 X: 2 Y: 18\nXXXXXXXXXX\nX   \u221e    X\nX XXXXXX X\nX\u221e      RX\nXXXX  XXXX\nX        X\nX        X\nX    \u221e M X\nXXX    XXX\nXe   \u221e  PX\nX       PX\nXXXXX XXXX\nX     X  X\nX XXXXX XX\nX     m  X\nXXXXXX XXX\nXTTX \u221e X X\nXTTXX XX X\nX H      X\nXXXXXXXXXX\n", "Health: 9 X: 1 Y: 18\nXXXXXXXXXX\nX   \u221e    X\nX XXXXXX X\nX\u221e      RX\nXXXX  XXXX\nX        X\nX        X\nX    \u221e M X\nXXX    XXX\nXe   \u221e  PX\nX       PX\nXXXXX XXXX\nX     X  X\nX XXXXX XX\nX        X\nXXXXXXmXXX\nXTTX \u221e X X\nXTTXX XX X\nXH       X\nXXXXXXXXXX\n", "Health: 9 X: 1 Y: 17\nXXXXXXXXXX\nX   \u221e    X\nX XXXXXX X\nX\u221e      RX\nXXXX  XXXX\nX        X\nX        X\nX    \u221e M X\nXXX    XXX\nXe   \u221e  PX\nX       PX\nXXXXX XXXX\nX     X  X\nX XXXXX XX\nX        X\nXXXXXX XXX\nXTTX \u221emX X\nX TXX XX X\nX        X\nXXXXXXXXXX\n", "Health: 9 X: 1 Y: 16\nXXXXXXXXXX\nX   \u221e    X\nX XXXXXX X\nX\u221e      RX\nXXXX  XXXX\nX        X\nX        X\nX    \u221e M X\nXXX    XXX\nXe   \u221e  PX\nX       PX\nXXXXX XXXX\nX     X  X\nX XXXXX XX\nX        X\nXXXXXX XXX\nX TX \u221e X X\nX TXX XX X\nX        X\nXXXXXXXXXX\n", "Health: 9 X: 2 Y: 16\nXXXXXXXXXX\nX   \u221e    X\nX XXXXXX X\nX\u221e      RX\nXXXX  XXXX\nX        X\nX        X\nX    \u221e M X\nXXX    XXX\nXe   \u221e  PX\nX       PX\nXXXXX XXXX\nX     X  X\nX XXXXX XX\nX        X\nXXXXXX XXX\nX  X \u221e X X\nX TXXmXX X\nX        X\nXXXXXXXXXX\n", "Health: 9 X: 2 Y: 17\nXXXXXXXXXX\nX   \u221e    X\nX XXXXXX X\nX\u221e      RX\nXXXX  XXXX\nX        X\nX        X\nX    \u221e M X\nXXX    XXX\nXe   \u221e  PX\nX       PX\nXXXXX XXXX\nX     X  X\nX XXXXX XX\nX        X\nXXXXXX XXX\nX  X \u221e X X\nX  XX XX X\nX    m   X\nXXXXXXXXXX\n", "Health: 9 X: 2 Y: 18\nXXXXXXXXXX\nX   \u221e    X\nX XXXXXX X\nX\u221e      RX\nXXXX  XXXX\nX        X\nX        X\nX    \u221e M X\nXXX    XXX\nXe   \u221e  PX\nX       PX\nXXXXX XXXX\nX     X  X\nX XXXXX XX\nX        X\nXXXXXX XXX\nX  X \u221e X X\nX  XX XX X\nX H m    X\nXXXXXXXXXX\n", "Health: 9 X: 2 Y: 18\nXXXXXXXXXX\nX   \u221e    X\nX XXXXXX X\nX\u221e      RX\nXXXX  XXXX\nX        X\nX        X\nX    \u221e M X\nXXX    XXX\nXe   \u221e  PX\nX       PX\nXXXXX XXXX\nX     X  X\nX XXXXX XX\nX        X\nXXXXXX XXX\nX  X \u221e X X\nX  XX XX X\nX H m    X\nXXXXXXXXXX\n", "Health: 9 X: 3 Y: 18\nXXXXXXXXXX\nX   \u221e    X\nX XXXXXX X\nX\u221e      RX\nXXXX  XXXX\nX        X\nX        X\nX    \u221e M X\nXXX    XXX\nXe   \u221e  PX\nX       PX\nXXXXX XXXX\nX     X  X\nX XXXXX XX\nX        X\nXXXXXX XXX\nX  X \u221e X X\nX  XX XX X\nX  Hm    X\nXXXXXXXXXX\n", "Health: 9 X: 4 Y: 18\nXXXXXXXXXX\nX   \u221e    X\nX XXXXXX X\nX\u221e      RX\nXXXX  XXXX\nX        X\nX        X\nX    \u221e M X\nXXX    XXX\nXe   \u221e  PX\nX       PX\nXXXXX XXXX\nX     X  X\nX XXXXX XX\nX        X\nXXXXXX XXX\nX  X \u221e X X\nX  XX XX X\nX   m    X\nXXXXXXXXXX\n", "Health: 9 X: 5 Y: 18\nXXXXXXXXXX\nX   \u221e    X\nX XXXXXX X\nX\u221e      RX\nXXXX  XXXX\nX        X\nX        X\nX    \u221e M X\nXXX    XXX\nXe   \u221e  PX\nX       PX\nXXXXX XXXX\nX     X  X\nX XXXXX XX\nX        X\nXXXXXX XXX\nX  X \u221e X X\nX  XX XX X\nX   mH   X\nXXXXXXXXXX\n", "Health: 9 X: 6 Y: 18\nXXXXXXXXXX\nX   \u221e    X\nX XXXXXX X\nX\u221e      RX\nXXXX  XXXX\nX        X\nX        X\nX    \u221e M X\nXXX    XXX\nXe   \u221e  PX\nX       PX\nXXXXX XXXX\nX     X  X\nX XXXXX XX\nX        X\nXXXXXX XXX\nX  X \u221e X X\nX  XX XX X\nX   m H  X\nXXXXXXXXXX\n", "Health: 8 X: 5 Y: 18\nXXXXXXXXXX\nX   \u221e    X\nX XXXXXX X\nX\u221e      RX\nXXXX  XXXX\nX        X\nX        X\nX    \u221e M X\nXXX    XXX\nXe   \u221e  PX\nX       PX\nXXXXX XXXX\nX     X  X\nX XXXXX XX\nX        X\nXXXXXX XXX\nX  X \u221e X X\nX  XX XX X\nX   mH   X\nXXXXXXXXXX\n", "Health: 8 X: 5 Y: 17\nXXXXXXXXXX\nX   \u221e    X\nX XXXXXX X\nX\u221e      RX\nXXXX  XXXX\nX        X\nX        X\nX    \u221e M X\nXXX    XXX\nXe   \u221e  PX\nX       PX\nXXXXX XXXX\nX     X  X\nX XXXXX XX\nX        X\nXXXXXX XXX\nX  X \u221e X X\nX  XXHXX X\nX   m    X\nXXXXXXXXXX\n", "Health: 8 X: 5 Y: 16\nXXXXXXXXXX\nX   \u221e    X\nX XXXXXX X\nX\u221e      RX\nXXXX  XXXX\nX        X\nX        X\nX    \u221e M X\nXXX    XXX\nXe   \u221e  PX\nX       PX\nXXXXX XXXX\nX     X  X\nX XXXXX XX\nX        X\nXXXXXX XXX\nX  X \u221e X X\nX  XX XX X\nX   m    X\nXXXXXXXXXX\n", "Health: 8 X: 6 Y: 16\nXXXXXXXXXX\nX   \u221e    X\nX XXXXXX X\nX\u221e      RX\nXXXX  XXXX\nX        X\nX        X\nX    \u221e M X\nXXX    XXX\nXe   \u221e  PX\nX       PX\nXXXXX XXXX\nX     X  X\nX XXXXX XX\nX        X\nXXXXXX XXX\nX  X \u221eHX X\nX  XX XX X\nX   m    X\nXXXXXXXXXX\n", "Health: 8 X: 6 Y: 15\nXXXXXXXXXX\nX   \u221e    X\nX XXXXXX X\nX\u221e      RX\nXXXX  XXXX\nX        X\nX        X\nX    \u221e M X\nXXX    XXX\nXe   \u221e  PX\nX       PX\nXXXXX XXXX\nX     X  X\nX XXXXX XX\nX        X\nXXXXXXHXXX\nX  X \u221e X X\nX  XX XX X\nX   m    X\nXXXXXXXXXX\n", "Health: 8 X: 6 Y: 14\nXXXXXXXXXX\nX   \u221e    X\nX XXXXXX X\nX\u221e      RX\nXXXX  XXXX\nX        X\nX        X\nX    \u221e M X\nXXX    XXX\nXe   \u221e  PX\nX       PX\nXXXXX XXXX\nX     X  X\nX XXXXX XX\nX     H  X\nXXXXXX XXX\nX  X \u221e X X\nX  XX XX X\nX   m    X\nXXXXXXXXXX\n", "Health: 8 X: 5 Y: 14\nXXXXXXXXXX\nX   \u221e    X\nX XXXXXX X\nX\u221e      RX\nXXXX  XXXX\nX        X\nX        X\nX    \u221e M X\nXXX    XXX\nXe   \u221e  PX\nX       PX\nXXXXX XXXX\nX     X  X\nX XXXXX XX\nX    H   X\nXXXXXX XXX\nX  X \u221e X X\nX  XX XX X\nX    m   X\nXXXXXXXXXX\n", "Health: 8 X: 4 Y: 14\nXXXXXXXXXX\nX   \u221e    X\nX XXXXXX X\nX\u221e      RX\nXXXX  XXXX\nX        X\nX        X\nX    \u221e M X\nXXX    XXX\nXe   \u221e  PX\nX       PX\nXXXXX XXXX\nX     X  X\nX XXXXX XX\nX   H    X\nXXXXXX XXX\nX  X \u221e X X\nX  XXmXX X\nX        X\nXXXXXXXXXX\n", "Health: 8 X: 3 Y: 14\nXXXXXXXXXX\nX   \u221e    X\nX XXXXXX X\nX\u221e      RX\nXXXX  XXXX\nX        X\nX        X\nX    \u221e M X\nXXX    XXX\nXe   \u221e  PX\nX       PX\nXXXXX XXXX\nX     X  X\nX XXXXX XX\nX  H     X\nXXXXXX XXX\nX  X \u221e X X\nX  XX XX X\nX        X\nXXXXXXXXXX\n", "Health: 8 X: 2 Y: 14\nXXXXXXXXXX\nX   \u221e    X\nX XXXXXX X\nX\u221e      RX\nXXXX  XXXX\nX        X\nX        X\nX    \u221e M X\nXXX    XXX\nXe   \u221e  PX\nX       PX\nXXXXX XXXX\nX     X  X\nX XXXXX XX\nX H      X\nXXXXXX XXX\nX  X \u221emX X\nX  XX XX X\nX        X\nXXXXXXXXXX\n", "Health: 8 X: 1 Y: 14\nXXXXXXXXXX\nX   \u221e    X\nX XXXXXX X\nX\u221e      RX\nXXXX  XXXX\nX        X\nX        X\nX    \u221e M X\nXXX    XXX\nXe   \u221e  PX\nX       PX\nXXXXX XXXX\nX     X  X\nX XXXXX XX\nXH       X\nXXXXXXmXXX\nX  X \u221e X X\nX  XX XX X\nX        X\nXXXXXXXXXX\n", "Health: 8 X: 1 Y: 13\nXXXXXXXXXX\nX   \u221e    X\nX XXXXXX X\nX\u221e      RX\nXXXX  XXXX\nX        X\nX        X\nX    \u221e M X\nXXX    XXX\nXe   \u221e  PX\nX       PX\nXXXXX XXXX\nX     X  X\nXHXXXXX XX\nX     m  X\nXXXXXX XXX\nX  X \u221e X X\nX  XX XX X\nX        X\nXXXXXXXXXX\n", "Health: 8 X: 1 Y: 12\nXXXXXXXXXX\nX   \u221e    X\nX XXXXXX X\nX\u221e      RX\nXXXX  XXXX\nX        X\nX        X\nX    \u221e M X\nXXX    XXX\nXe   \u221e  PX\nX       PX\nXXXXX XXXX\nXH    X  X\nX XXXXX XX\nX    m   X\nXXXXXX XXX\nX  X \u221e X X\nX  XX XX X\nX        X\nXXXXXXXXXX\n", "Health: 8 X: 2 Y: 12\nXXXXXXXXXX\nX   \u221e    X\nX XXXXXX X\nX\u221e      RX\nXXXX  XXXX\nX        X\nX        X\nX    \u221e M X\nXXX    XXX\nXe   \u221e  PX\nX       PX\nXXXXX XXXX\nX H   X  X\nX XXXXX XX\nX   m    X\nXXXXXX XXX\nX  X \u221e X X\nX  XX XX X\nX        X\nXXXXXXXXXX\n", "Health: 8 X: 3 Y: 12\nXXXXXXXXXX\nX   \u221e    X\nX XXXXXX X\nX\u221e      RX\nXXXX  XXXX\nX        X\nX        X\nX    \u221e M X\nXXX    XXX\nXe   \u221e  PX\nX       PX\nXXXXX XXXX\nX  H  X  X\nX XXXXX XX\nX  m     X\nXXXXXX XXX\nX  X \u221e X X\nX  XX XX X\nX        X\nXXXXXXXXXX\n", "Health: 8 X: 4 Y: 12\nXXXXXXXXXX\nX   \u221e    X\nX XXXXXX X\nX\u221e      RX\nXXXX  XXXX\nX        X\nX        X\nX    \u221e M X\nXXX    XXX\nXe   \u221e  PX\nX       PX\nXXXXX XXXX\nX   H X  X\nX XXXXX XX\nX m      X\nXXXXXX XXX\nX  X \u221e X X\nX  XX XX X\nX        X\nXXXXXXXXXX\n", "Health: 8 X: 5 Y: 12\nXXXXXXXXXX\nX   \u221e    X\nX XXXXXX X\nX\u221e      RX\nXXXX  XXXX\nX        X\nX        X\nX    \u221e M X\nXXX    XXX\nXe   \u221e  PX\nX       PX\nXXXXX XXXX\nX    HX  X\nX XXXXX XX\nXm       X\nXXXXXX XXX\nX  X \u221e X X\nX  XX XX X\nX        X\nXXXXXXXXXX\n", "Health: 8 X: 5 Y: 11\nXXXXXXXXXX\nX   \u221e    X\nX XXXXXX X\nX\u221e      RX\nXXXX  XXXX\nX        X\nX        X\nX    \u221e M X\nXXX    XXX\nXe   \u221e  PX\nX       PX\nXXXXXHXXXX\nX     X  X\nXmXXXXX XX\nX        X\nXXXXXX XXX\nX  X \u221e X X\nX  XX XX X\nX        X\nXXXXXXXXXX\n", "Health: 8 X: 5 Y: 10\nXXXXXXXXXX\nX   \u221e    X\nX XXXXXX X\nX\u221e      RX\nXXXX  XXXX\nX        X\nX        X\nX    \u221e M X\nXXX    XXX\nXe   \u221e  PX\nX    H  PX\nXXXXX XXXX\nXm    X  X\nX XXXXX XX\nX        X\nXXXXXX XXX\nX  X \u221e X X\nX  XX XX X\nX        X\nXXXXXXXXXX\n", "Health: 8 X: 6 Y: 10\nXXXXXXXXXX\nX   \u221e    X\nX XXXXXX X\nX\u221e      RX\nXXXX  XXXX\nX        X\nX        X\nX    \u221e M X\nXXX    XXX\nXe   \u221e  PX\nX     H PX\nXXXXX XXXX\nX m   X  X\nX XXXXX XX\nX        X\nXXXXXX XXX\nX  X \u221e X X\nX  XX XX X\nX        X\nXXXXXXXXXX\n", "Health: 8 X: 7 Y: 10\nXXXXXXXXXX\nX   \u221e    X\nX XXXXXX X\nX\u221e      RX\nXXXX  XXXX\nX        X\nX        X\nX    \u221e M X\nXXX    XXX\nXe   \u221e  PX\nX      HPX\nXXXXX XXXX\nX  m  X  X\nX XXXXX XX\nX        X\nXXXXXX XXX\nX  X \u221e X X\nX  XX XX X\nX        X\nXXXXXXXXXX\n", "Health: 10 X: 8 Y: 10\nXXXXXXXXXX\nX   \u221e    X\nX XXXXXX X\nX\u221e      RX\nXXXX  XXXX\nX        X\nX        X\nX    \u221e M X\nXXX    XXX\nXe   \u221e  PX\nX        X\nXXXXX XXXX\nX   m X  X\nX XXXXX XX\nX        X\nXXXXXX XXX\nX  X \u221e X X\nX  XX XX X\nX        X\nXXXXXXXXXX\n", "Health: 10 X: 7 Y: 10\nXXXXXXXXXX\nX   \u221e    X\nX XXXXXX X\nX\u221e      RX\nXXXX  XXXX\nX        X\nX        X\nX    \u221e M X\nXXX    XXX\nXe   \u221e  PX\nX      H X\nXXXXX XXXX\nX    mX  X\nX XXXXX XX\nX        X\nXXXXXX XXX\nX  X \u221e X X\nX  XX XX X\nX        X\nXXXXXXXXXX\n", "Health: 10 X: 7 Y: 9\nXXXXXXXXXX\nX   \u221e    X\nX XXXXXX X\nX\u221e      RX\nXXXX  XXXX\nX        X\nX        X\nX    \u221e M X\nXXX    XXX\nXe   \u221e HPX\nX        X\nXXXXXmXXXX\nX     X  X\nX XXXXX XX\nX        X\nXXXXXX XXX\nX  X \u221e X X\nX  XX XX X\nX        X\nXXXXXXXXXX\n", "Health: 10 X: 6 Y: 9\nXXXXXXXXXX\nX   \u221e    X\nX XXXXXX X\nX\u221e      RX\nXXXX  XXXX\nX        X\nX        X\nX    \u221e M X\nXXX    XXX\nXe   \u221eH PX\nX    m   X\nXXXXX XXXX\nX     X  X\nX XXXXX XX\nX        X\nXXXXXX XXX\nX  X \u221e X X\nX  XX XX X\nX        X\nXXXXXXXXXX\n", "Health: 10 X: 7 Y: 9\nXXXXXXXXXX\nX   \u221e    X\nX XXXXXX X\nX\u221e      RX\nXXXX  XXXX\nX        X\nX        X\nX    \u221e M X\nXXX    XXX\nXe   \u221e HPX\nX        X\nXXXXX XXXX\nX     X  X\nX XXXXX XX\nX        X\nXXXXXX XXX\nX  X \u221e X X\nX  XX XX X\nX        X\nXXXXXXXXXX\n", "Health: 10 X: 7 Y: 9\nXXXXXXXXXX\nX   \u221e    X\nX XXXXXX X\nX\u221e      RX\nXXXX  XXXX\nX        X\nX        X\nX    \u221e M X\nXXX    XXX\nXe   \u221e HPX\nX        X\nXXXXX XXXX\nX     X  X\nX XXXXX XX\nX        X\nXXXXXX XXX\nX  X \u221e X X\nX  XX XX X\nX        X\nXXXXXXXXXX\n", "Health: 10 X: 6 Y: 9\nXXXXXXXXXX\nX   \u221e    X\nX XXXXXX X\nX\u221e      RX\nXXXX  XXXX\nX        X\nX        X\nX    \u221e M X\nXXX    XXX\nXe   \u221eH PX\nX        X\nXXXXX XXXX\nX     X  X\nX XXXXX XX\nX        X\nXXXXXX XXX\nX  X \u221e X X\nX  XX XX X\nX        X\nXXXXXXXXXX\n", "Health: 10 X: 5 Y: 9\nXXXXXXXXXX\nX   \u221e    X\nX XXXXXX X\nX\u221e      RX\nXXXX  XXXX\nX        X\nX        X\nX    \u221e M X\nXXX    XXX\nXe   \u221e  PX\nX        X\nXXXXX XXXX\nX     X  X\nX XXXXX XX\nX        X\nXXXXXX XXX\nX  X \u221e X X\nX  XX XX X\nX        X\nXXXXXXXXXX\n", "Health: 10 X: 4 Y: 9\nXXXXXXXXXX\nX   \u221e    X\nX XXXXXX X\nX\u221e      RX\nXXXX  XXXX\nX        X\nX        X\nX    \u221eM  X\nXXX    XXX\nXe  H\u221e  PX\nX        X\nXXXXX XXXX\nX     X  X\nX XXXXX XX\nX        X\nXXXXXX XXX\nX  X \u221e X X\nX  XX XX X\nX        X\nXXXXXXXXXX\n", "Health: 10 X: 3 Y: 9\nXXXXXXXXXX\nX   \u221e    X\nX XXXXXX X\nX\u221e      RX\nXXXX  XXXX\nX        X\nX        X\nX    M   X\nXXX    XXX\nXe H \u221e  PX\nX        X\nXXXXX XXXX\nX     X  X\nX XXXXX XX\nX        X\nXXXXXX XXX\nX  X \u221e X X\nX  XX XX X\nX        X\nXXXXXXXXXX\n", "Health: 10 X: 2 Y: 9\nXXXXXXXXXX\nX   \u221e    X\nX XXXXXX X\nX\u221e      RX\nXXXX  XXXX\nX        X\nX        X\nX   M\u221e   X\nXXX    XXX\nXeH m\u221e  PX\nX        X\nXXXXX XXXX\nX     X  X\nX XXXXX XX\nX        X\nXXXXXX XXX\nX  X \u221e X X\nX  XX XX X\nX        X\nXXXXXXXXXX\n", "Health: 10 X: 1 Y: 9\nXXXXXXXXXX\nX   \u221e    X\nX XXXXXX X\nX\u221e      RX\nXXXX  XXXX\nX        X\nX        X\nX   M\u221e   X\nXXX    XXX\nXe m \u221e  PX\nX        X\nXXXXX XXXX\nX     X  X\nX XXXXX XX\nX        X\nXXXXXX XXX\nX  X \u221e X X\nX  XX XX X\nX        X\nXXXXXXXXXX\n"], "map_number": 102}], "timestamp": "10-Aug-2021 16:04:16.990388", "ip": "72.74.225.165"}